{"reward": 23.0, "timestamp": 1711468807, "checkpoint_dir_name": null, "done": false, "training_iteration": 1, "trial_id": "5ed6c2ee", "date": "2024-03-26_17-00-07", "time_this_iter_s": 0.981590986251831, "time_total_s": 0.981590986251831, "pid": 436, "hostname": "Nicolass-Air.technicolor.net", "node_ip": "127.0.0.1", "config": {"exp_name": "QREPS", "seed": 1, "torch_deterministic": true, "cuda": true, "track": false, "wandb_project_name": "QREPS_CartPole-v1", "wandb_entity": "TFG", "capture_video": false, "env_id": "CartPole-v1", "total_timesteps": 200, "num_updates": 40, "buffer_size": 10000, "update_epochs": 300, "update_policy_epochs": 100, "num_rollouts": 1, "num_envs": 1, "gamma": 0.9, "policy_lr_start": 0.007649592149703917, "policy_lr_end": 2.7271824981526242e-05, "q_lr_start": 0.013582391871765085, "q_lr_end": 0.0002058258115096068, "alpha": 0.6565128343323917, "eta": 3.3419695298808128, "autotune": false, "target_entropy_scale": 0.1, "linear_schedule": false, "__trial_index__": 2}, "time_since_restore": 0.981590986251831, "iterations_since_restore": 1}
{"reward": 23.0, "timestamp": 1711468809, "checkpoint_dir_name": null, "done": false, "training_iteration": 2, "trial_id": "5ed6c2ee", "date": "2024-03-26_17-00-09", "time_this_iter_s": 1.191816806793213, "time_total_s": 2.173407793045044, "pid": 436, "hostname": "Nicolass-Air.technicolor.net", "node_ip": "127.0.0.1", "config": {"exp_name": "QREPS", "seed": 1, "torch_deterministic": true, "cuda": true, "track": false, "wandb_project_name": "QREPS_CartPole-v1", "wandb_entity": "TFG", "capture_video": false, "env_id": "CartPole-v1", "total_timesteps": 200, "num_updates": 40, "buffer_size": 10000, "update_epochs": 300, "update_policy_epochs": 100, "num_rollouts": 1, "num_envs": 1, "gamma": 0.9, "policy_lr_start": 0.007649592149703917, "policy_lr_end": 2.7271824981526242e-05, "q_lr_start": 0.013582391871765085, "q_lr_end": 0.0002058258115096068, "alpha": 0.6565128343323917, "eta": 3.3419695298808128, "autotune": false, "target_entropy_scale": 0.1, "linear_schedule": false, "__trial_index__": 2}, "time_since_restore": 2.173407793045044, "iterations_since_restore": 2}
{"reward": 21.0, "timestamp": 1711468810, "checkpoint_dir_name": null, "done": false, "training_iteration": 3, "trial_id": "5ed6c2ee", "date": "2024-03-26_17-00-10", "time_this_iter_s": 1.0729670524597168, "time_total_s": 3.2463748455047607, "pid": 436, "hostname": "Nicolass-Air.technicolor.net", "node_ip": "127.0.0.1", "config": {"exp_name": "QREPS", "seed": 1, "torch_deterministic": true, "cuda": true, "track": false, "wandb_project_name": "QREPS_CartPole-v1", "wandb_entity": "TFG", "capture_video": false, "env_id": "CartPole-v1", "total_timesteps": 200, "num_updates": 40, "buffer_size": 10000, "update_epochs": 300, "update_policy_epochs": 100, "num_rollouts": 1, "num_envs": 1, "gamma": 0.9, "policy_lr_start": 0.007649592149703917, "policy_lr_end": 2.7271824981526242e-05, "q_lr_start": 0.013582391871765085, "q_lr_end": 0.0002058258115096068, "alpha": 0.6565128343323917, "eta": 3.3419695298808128, "autotune": false, "target_entropy_scale": 0.1, "linear_schedule": false, "__trial_index__": 2}, "time_since_restore": 3.2463748455047607, "iterations_since_restore": 3}
{"reward": 21.0, "timestamp": 1711468811, "checkpoint_dir_name": null, "done": false, "training_iteration": 4, "trial_id": "5ed6c2ee", "date": "2024-03-26_17-00-11", "time_this_iter_s": 1.1478219032287598, "time_total_s": 4.3941967487335205, "pid": 436, "hostname": "Nicolass-Air.technicolor.net", "node_ip": "127.0.0.1", "config": {"exp_name": "QREPS", "seed": 1, "torch_deterministic": true, "cuda": true, "track": false, "wandb_project_name": "QREPS_CartPole-v1", "wandb_entity": "TFG", "capture_video": false, "env_id": "CartPole-v1", "total_timesteps": 200, "num_updates": 40, "buffer_size": 10000, "update_epochs": 300, "update_policy_epochs": 100, "num_rollouts": 1, "num_envs": 1, "gamma": 0.9, "policy_lr_start": 0.007649592149703917, "policy_lr_end": 2.7271824981526242e-05, "q_lr_start": 0.013582391871765085, "q_lr_end": 0.0002058258115096068, "alpha": 0.6565128343323917, "eta": 3.3419695298808128, "autotune": false, "target_entropy_scale": 0.1, "linear_schedule": false, "__trial_index__": 2}, "time_since_restore": 4.3941967487335205, "iterations_since_restore": 4}
{"reward": 21.0, "timestamp": 1711468812, "checkpoint_dir_name": null, "done": false, "training_iteration": 5, "trial_id": "5ed6c2ee", "date": "2024-03-26_17-00-12", "time_this_iter_s": 1.099515676498413, "time_total_s": 5.493712425231934, "pid": 436, "hostname": "Nicolass-Air.technicolor.net", "node_ip": "127.0.0.1", "config": {"exp_name": "QREPS", "seed": 1, "torch_deterministic": true, "cuda": true, "track": false, "wandb_project_name": "QREPS_CartPole-v1", "wandb_entity": "TFG", "capture_video": false, "env_id": "CartPole-v1", "total_timesteps": 200, "num_updates": 40, "buffer_size": 10000, "update_epochs": 300, "update_policy_epochs": 100, "num_rollouts": 1, "num_envs": 1, "gamma": 0.9, "policy_lr_start": 0.007649592149703917, "policy_lr_end": 2.7271824981526242e-05, "q_lr_start": 0.013582391871765085, "q_lr_end": 0.0002058258115096068, "alpha": 0.6565128343323917, "eta": 3.3419695298808128, "autotune": false, "target_entropy_scale": 0.1, "linear_schedule": false, "__trial_index__": 2}, "time_since_restore": 5.493712425231934, "iterations_since_restore": 5}
{"reward": 21.0, "timestamp": 1711468813, "checkpoint_dir_name": null, "done": false, "training_iteration": 6, "trial_id": "5ed6c2ee", "date": "2024-03-26_17-00-13", "time_this_iter_s": 1.1426420211791992, "time_total_s": 6.636354446411133, "pid": 436, "hostname": "Nicolass-Air.technicolor.net", "node_ip": "127.0.0.1", "config": {"exp_name": "QREPS", "seed": 1, "torch_deterministic": true, "cuda": true, "track": false, "wandb_project_name": "QREPS_CartPole-v1", "wandb_entity": "TFG", "capture_video": false, "env_id": "CartPole-v1", "total_timesteps": 200, "num_updates": 40, "buffer_size": 10000, "update_epochs": 300, "update_policy_epochs": 100, "num_rollouts": 1, "num_envs": 1, "gamma": 0.9, "policy_lr_start": 0.007649592149703917, "policy_lr_end": 2.7271824981526242e-05, "q_lr_start": 0.013582391871765085, "q_lr_end": 0.0002058258115096068, "alpha": 0.6565128343323917, "eta": 3.3419695298808128, "autotune": false, "target_entropy_scale": 0.1, "linear_schedule": false, "__trial_index__": 2}, "time_since_restore": 6.636354446411133, "iterations_since_restore": 6}
{"reward": 21.0, "timestamp": 1711468814, "checkpoint_dir_name": null, "done": false, "training_iteration": 7, "trial_id": "5ed6c2ee", "date": "2024-03-26_17-00-14", "time_this_iter_s": 1.1065559387207031, "time_total_s": 7.742910385131836, "pid": 436, "hostname": "Nicolass-Air.technicolor.net", "node_ip": "127.0.0.1", "config": {"exp_name": "QREPS", "seed": 1, "torch_deterministic": true, "cuda": true, "track": false, "wandb_project_name": "QREPS_CartPole-v1", "wandb_entity": "TFG", "capture_video": false, "env_id": "CartPole-v1", "total_timesteps": 200, "num_updates": 40, "buffer_size": 10000, "update_epochs": 300, "update_policy_epochs": 100, "num_rollouts": 1, "num_envs": 1, "gamma": 0.9, "policy_lr_start": 0.007649592149703917, "policy_lr_end": 2.7271824981526242e-05, "q_lr_start": 0.013582391871765085, "q_lr_end": 0.0002058258115096068, "alpha": 0.6565128343323917, "eta": 3.3419695298808128, "autotune": false, "target_entropy_scale": 0.1, "linear_schedule": false, "__trial_index__": 2}, "time_since_restore": 7.742910385131836, "iterations_since_restore": 7}
{"reward": 21.0, "timestamp": 1711468815, "checkpoint_dir_name": null, "done": false, "training_iteration": 8, "trial_id": "5ed6c2ee", "date": "2024-03-26_17-00-15", "time_this_iter_s": 1.2052879333496094, "time_total_s": 8.948198318481445, "pid": 436, "hostname": "Nicolass-Air.technicolor.net", "node_ip": "127.0.0.1", "config": {"exp_name": "QREPS", "seed": 1, "torch_deterministic": true, "cuda": true, "track": false, "wandb_project_name": "QREPS_CartPole-v1", "wandb_entity": "TFG", "capture_video": false, "env_id": "CartPole-v1", "total_timesteps": 200, "num_updates": 40, "buffer_size": 10000, "update_epochs": 300, "update_policy_epochs": 100, "num_rollouts": 1, "num_envs": 1, "gamma": 0.9, "policy_lr_start": 0.007649592149703917, "policy_lr_end": 2.7271824981526242e-05, "q_lr_start": 0.013582391871765085, "q_lr_end": 0.0002058258115096068, "alpha": 0.6565128343323917, "eta": 3.3419695298808128, "autotune": false, "target_entropy_scale": 0.1, "linear_schedule": false, "__trial_index__": 2}, "time_since_restore": 8.948198318481445, "iterations_since_restore": 8}
{"reward": 21.0, "timestamp": 1711468817, "checkpoint_dir_name": null, "done": false, "training_iteration": 9, "trial_id": "5ed6c2ee", "date": "2024-03-26_17-00-17", "time_this_iter_s": 1.143301010131836, "time_total_s": 10.091499328613281, "pid": 436, "hostname": "Nicolass-Air.technicolor.net", "node_ip": "127.0.0.1", "config": {"exp_name": "QREPS", "seed": 1, "torch_deterministic": true, "cuda": true, "track": false, "wandb_project_name": "QREPS_CartPole-v1", "wandb_entity": "TFG", "capture_video": false, "env_id": "CartPole-v1", "total_timesteps": 200, "num_updates": 40, "buffer_size": 10000, "update_epochs": 300, "update_policy_epochs": 100, "num_rollouts": 1, "num_envs": 1, "gamma": 0.9, "policy_lr_start": 0.007649592149703917, "policy_lr_end": 2.7271824981526242e-05, "q_lr_start": 0.013582391871765085, "q_lr_end": 0.0002058258115096068, "alpha": 0.6565128343323917, "eta": 3.3419695298808128, "autotune": false, "target_entropy_scale": 0.1, "linear_schedule": false, "__trial_index__": 2}, "time_since_restore": 10.091499328613281, "iterations_since_restore": 9}
{"reward": 21.0, "timestamp": 1711468818, "checkpoint_dir_name": null, "done": false, "training_iteration": 10, "trial_id": "5ed6c2ee", "date": "2024-03-26_17-00-18", "time_this_iter_s": 1.0590441226959229, "time_total_s": 11.150543451309204, "pid": 436, "hostname": "Nicolass-Air.technicolor.net", "node_ip": "127.0.0.1", "config": {"exp_name": "QREPS", "seed": 1, "torch_deterministic": true, "cuda": true, "track": false, "wandb_project_name": "QREPS_CartPole-v1", "wandb_entity": "TFG", "capture_video": false, "env_id": "CartPole-v1", "total_timesteps": 200, "num_updates": 40, "buffer_size": 10000, "update_epochs": 300, "update_policy_epochs": 100, "num_rollouts": 1, "num_envs": 1, "gamma": 0.9, "policy_lr_start": 0.007649592149703917, "policy_lr_end": 2.7271824981526242e-05, "q_lr_start": 0.013582391871765085, "q_lr_end": 0.0002058258115096068, "alpha": 0.6565128343323917, "eta": 3.3419695298808128, "autotune": false, "target_entropy_scale": 0.1, "linear_schedule": false, "__trial_index__": 2}, "time_since_restore": 11.150543451309204, "iterations_since_restore": 10}
{"reward": 21.0, "timestamp": 1711468819, "checkpoint_dir_name": null, "done": false, "training_iteration": 11, "trial_id": "5ed6c2ee", "date": "2024-03-26_17-00-19", "time_this_iter_s": 1.0555930137634277, "time_total_s": 12.206136465072632, "pid": 436, "hostname": "Nicolass-Air.technicolor.net", "node_ip": "127.0.0.1", "config": {"exp_name": "QREPS", "seed": 1, "torch_deterministic": true, "cuda": true, "track": false, "wandb_project_name": "QREPS_CartPole-v1", "wandb_entity": "TFG", "capture_video": false, "env_id": "CartPole-v1", "total_timesteps": 200, "num_updates": 40, "buffer_size": 10000, "update_epochs": 300, "update_policy_epochs": 100, "num_rollouts": 1, "num_envs": 1, "gamma": 0.9, "policy_lr_start": 0.007649592149703917, "policy_lr_end": 2.7271824981526242e-05, "q_lr_start": 0.013582391871765085, "q_lr_end": 0.0002058258115096068, "alpha": 0.6565128343323917, "eta": 3.3419695298808128, "autotune": false, "target_entropy_scale": 0.1, "linear_schedule": false, "__trial_index__": 2}, "time_since_restore": 12.206136465072632, "iterations_since_restore": 11}
{"reward": 21.0, "timestamp": 1711468820, "checkpoint_dir_name": null, "done": false, "training_iteration": 12, "trial_id": "5ed6c2ee", "date": "2024-03-26_17-00-20", "time_this_iter_s": 1.130300760269165, "time_total_s": 13.336437225341797, "pid": 436, "hostname": "Nicolass-Air.technicolor.net", "node_ip": "127.0.0.1", "config": {"exp_name": "QREPS", "seed": 1, "torch_deterministic": true, "cuda": true, "track": false, "wandb_project_name": "QREPS_CartPole-v1", "wandb_entity": "TFG", "capture_video": false, "env_id": "CartPole-v1", "total_timesteps": 200, "num_updates": 40, "buffer_size": 10000, "update_epochs": 300, "update_policy_epochs": 100, "num_rollouts": 1, "num_envs": 1, "gamma": 0.9, "policy_lr_start": 0.007649592149703917, "policy_lr_end": 2.7271824981526242e-05, "q_lr_start": 0.013582391871765085, "q_lr_end": 0.0002058258115096068, "alpha": 0.6565128343323917, "eta": 3.3419695298808128, "autotune": false, "target_entropy_scale": 0.1, "linear_schedule": false, "__trial_index__": 2}, "time_since_restore": 13.336437225341797, "iterations_since_restore": 12}
{"reward": 21.0, "timestamp": 1711468821, "checkpoint_dir_name": null, "done": false, "training_iteration": 13, "trial_id": "5ed6c2ee", "date": "2024-03-26_17-00-21", "time_this_iter_s": 1.0781660079956055, "time_total_s": 14.414603233337402, "pid": 436, "hostname": "Nicolass-Air.technicolor.net", "node_ip": "127.0.0.1", "config": {"exp_name": "QREPS", "seed": 1, "torch_deterministic": true, "cuda": true, "track": false, "wandb_project_name": "QREPS_CartPole-v1", "wandb_entity": "TFG", "capture_video": false, "env_id": "CartPole-v1", "total_timesteps": 200, "num_updates": 40, "buffer_size": 10000, "update_epochs": 300, "update_policy_epochs": 100, "num_rollouts": 1, "num_envs": 1, "gamma": 0.9, "policy_lr_start": 0.007649592149703917, "policy_lr_end": 2.7271824981526242e-05, "q_lr_start": 0.013582391871765085, "q_lr_end": 0.0002058258115096068, "alpha": 0.6565128343323917, "eta": 3.3419695298808128, "autotune": false, "target_entropy_scale": 0.1, "linear_schedule": false, "__trial_index__": 2}, "time_since_restore": 14.414603233337402, "iterations_since_restore": 13}
{"reward": 21.0, "timestamp": 1711468822, "checkpoint_dir_name": null, "done": false, "training_iteration": 14, "trial_id": "5ed6c2ee", "date": "2024-03-26_17-00-22", "time_this_iter_s": 1.1770639419555664, "time_total_s": 15.591667175292969, "pid": 436, "hostname": "Nicolass-Air.technicolor.net", "node_ip": "127.0.0.1", "config": {"exp_name": "QREPS", "seed": 1, "torch_deterministic": true, "cuda": true, "track": false, "wandb_project_name": "QREPS_CartPole-v1", "wandb_entity": "TFG", "capture_video": false, "env_id": "CartPole-v1", "total_timesteps": 200, "num_updates": 40, "buffer_size": 10000, "update_epochs": 300, "update_policy_epochs": 100, "num_rollouts": 1, "num_envs": 1, "gamma": 0.9, "policy_lr_start": 0.007649592149703917, "policy_lr_end": 2.7271824981526242e-05, "q_lr_start": 0.013582391871765085, "q_lr_end": 0.0002058258115096068, "alpha": 0.6565128343323917, "eta": 3.3419695298808128, "autotune": false, "target_entropy_scale": 0.1, "linear_schedule": false, "__trial_index__": 2}, "time_since_restore": 15.591667175292969, "iterations_since_restore": 14}
{"reward": 21.0, "timestamp": 1711468823, "checkpoint_dir_name": null, "done": false, "training_iteration": 15, "trial_id": "5ed6c2ee", "date": "2024-03-26_17-00-23", "time_this_iter_s": 1.0743381977081299, "time_total_s": 16.6660053730011, "pid": 436, "hostname": "Nicolass-Air.technicolor.net", "node_ip": "127.0.0.1", "config": {"exp_name": "QREPS", "seed": 1, "torch_deterministic": true, "cuda": true, "track": false, "wandb_project_name": "QREPS_CartPole-v1", "wandb_entity": "TFG", "capture_video": false, "env_id": "CartPole-v1", "total_timesteps": 200, "num_updates": 40, "buffer_size": 10000, "update_epochs": 300, "update_policy_epochs": 100, "num_rollouts": 1, "num_envs": 1, "gamma": 0.9, "policy_lr_start": 0.007649592149703917, "policy_lr_end": 2.7271824981526242e-05, "q_lr_start": 0.013582391871765085, "q_lr_end": 0.0002058258115096068, "alpha": 0.6565128343323917, "eta": 3.3419695298808128, "autotune": false, "target_entropy_scale": 0.1, "linear_schedule": false, "__trial_index__": 2}, "time_since_restore": 16.6660053730011, "iterations_since_restore": 15}
{"reward": 21.0, "timestamp": 1711468824, "checkpoint_dir_name": null, "done": false, "training_iteration": 16, "trial_id": "5ed6c2ee", "date": "2024-03-26_17-00-24", "time_this_iter_s": 1.1907341480255127, "time_total_s": 17.85673952102661, "pid": 436, "hostname": "Nicolass-Air.technicolor.net", "node_ip": "127.0.0.1", "config": {"exp_name": "QREPS", "seed": 1, "torch_deterministic": true, "cuda": true, "track": false, "wandb_project_name": "QREPS_CartPole-v1", "wandb_entity": "TFG", "capture_video": false, "env_id": "CartPole-v1", "total_timesteps": 200, "num_updates": 40, "buffer_size": 10000, "update_epochs": 300, "update_policy_epochs": 100, "num_rollouts": 1, "num_envs": 1, "gamma": 0.9, "policy_lr_start": 0.007649592149703917, "policy_lr_end": 2.7271824981526242e-05, "q_lr_start": 0.013582391871765085, "q_lr_end": 0.0002058258115096068, "alpha": 0.6565128343323917, "eta": 3.3419695298808128, "autotune": false, "target_entropy_scale": 0.1, "linear_schedule": false, "__trial_index__": 2}, "time_since_restore": 17.85673952102661, "iterations_since_restore": 16}
{"reward": 21.0, "timestamp": 1711468826, "checkpoint_dir_name": null, "done": false, "training_iteration": 17, "trial_id": "5ed6c2ee", "date": "2024-03-26_17-00-26", "time_this_iter_s": 1.1993539333343506, "time_total_s": 19.056093454360962, "pid": 436, "hostname": "Nicolass-Air.technicolor.net", "node_ip": "127.0.0.1", "config": {"exp_name": "QREPS", "seed": 1, "torch_deterministic": true, "cuda": true, "track": false, "wandb_project_name": "QREPS_CartPole-v1", "wandb_entity": "TFG", "capture_video": false, "env_id": "CartPole-v1", "total_timesteps": 200, "num_updates": 40, "buffer_size": 10000, "update_epochs": 300, "update_policy_epochs": 100, "num_rollouts": 1, "num_envs": 1, "gamma": 0.9, "policy_lr_start": 0.007649592149703917, "policy_lr_end": 2.7271824981526242e-05, "q_lr_start": 0.013582391871765085, "q_lr_end": 0.0002058258115096068, "alpha": 0.6565128343323917, "eta": 3.3419695298808128, "autotune": false, "target_entropy_scale": 0.1, "linear_schedule": false, "__trial_index__": 2}, "time_since_restore": 19.056093454360962, "iterations_since_restore": 17}
{"reward": 21.0, "timestamp": 1711468827, "checkpoint_dir_name": null, "done": false, "training_iteration": 18, "trial_id": "5ed6c2ee", "date": "2024-03-26_17-00-27", "time_this_iter_s": 1.2035129070281982, "time_total_s": 20.25960636138916, "pid": 436, "hostname": "Nicolass-Air.technicolor.net", "node_ip": "127.0.0.1", "config": {"exp_name": "QREPS", "seed": 1, "torch_deterministic": true, "cuda": true, "track": false, "wandb_project_name": "QREPS_CartPole-v1", "wandb_entity": "TFG", "capture_video": false, "env_id": "CartPole-v1", "total_timesteps": 200, "num_updates": 40, "buffer_size": 10000, "update_epochs": 300, "update_policy_epochs": 100, "num_rollouts": 1, "num_envs": 1, "gamma": 0.9, "policy_lr_start": 0.007649592149703917, "policy_lr_end": 2.7271824981526242e-05, "q_lr_start": 0.013582391871765085, "q_lr_end": 0.0002058258115096068, "alpha": 0.6565128343323917, "eta": 3.3419695298808128, "autotune": false, "target_entropy_scale": 0.1, "linear_schedule": false, "__trial_index__": 2}, "time_since_restore": 20.25960636138916, "iterations_since_restore": 18}
{"reward": 21.0, "timestamp": 1711468828, "checkpoint_dir_name": null, "done": false, "training_iteration": 19, "trial_id": "5ed6c2ee", "date": "2024-03-26_17-00-28", "time_this_iter_s": 1.1439487934112549, "time_total_s": 21.403555154800415, "pid": 436, "hostname": "Nicolass-Air.technicolor.net", "node_ip": "127.0.0.1", "config": {"exp_name": "QREPS", "seed": 1, "torch_deterministic": true, "cuda": true, "track": false, "wandb_project_name": "QREPS_CartPole-v1", "wandb_entity": "TFG", "capture_video": false, "env_id": "CartPole-v1", "total_timesteps": 200, "num_updates": 40, "buffer_size": 10000, "update_epochs": 300, "update_policy_epochs": 100, "num_rollouts": 1, "num_envs": 1, "gamma": 0.9, "policy_lr_start": 0.007649592149703917, "policy_lr_end": 2.7271824981526242e-05, "q_lr_start": 0.013582391871765085, "q_lr_end": 0.0002058258115096068, "alpha": 0.6565128343323917, "eta": 3.3419695298808128, "autotune": false, "target_entropy_scale": 0.1, "linear_schedule": false, "__trial_index__": 2}, "time_since_restore": 21.403555154800415, "iterations_since_restore": 19}
{"reward": 21.0, "timestamp": 1711468829, "checkpoint_dir_name": null, "done": false, "training_iteration": 20, "trial_id": "5ed6c2ee", "date": "2024-03-26_17-00-29", "time_this_iter_s": 1.0319981575012207, "time_total_s": 22.435553312301636, "pid": 436, "hostname": "Nicolass-Air.technicolor.net", "node_ip": "127.0.0.1", "config": {"exp_name": "QREPS", "seed": 1, "torch_deterministic": true, "cuda": true, "track": false, "wandb_project_name": "QREPS_CartPole-v1", "wandb_entity": "TFG", "capture_video": false, "env_id": "CartPole-v1", "total_timesteps": 200, "num_updates": 40, "buffer_size": 10000, "update_epochs": 300, "update_policy_epochs": 100, "num_rollouts": 1, "num_envs": 1, "gamma": 0.9, "policy_lr_start": 0.007649592149703917, "policy_lr_end": 2.7271824981526242e-05, "q_lr_start": 0.013582391871765085, "q_lr_end": 0.0002058258115096068, "alpha": 0.6565128343323917, "eta": 3.3419695298808128, "autotune": false, "target_entropy_scale": 0.1, "linear_schedule": false, "__trial_index__": 2}, "time_since_restore": 22.435553312301636, "iterations_since_restore": 20}
{"reward": 21.0, "timestamp": 1711468830, "checkpoint_dir_name": null, "done": false, "training_iteration": 21, "trial_id": "5ed6c2ee", "date": "2024-03-26_17-00-30", "time_this_iter_s": 1.0078411102294922, "time_total_s": 23.443394422531128, "pid": 436, "hostname": "Nicolass-Air.technicolor.net", "node_ip": "127.0.0.1", "config": {"exp_name": "QREPS", "seed": 1, "torch_deterministic": true, "cuda": true, "track": false, "wandb_project_name": "QREPS_CartPole-v1", "wandb_entity": "TFG", "capture_video": false, "env_id": "CartPole-v1", "total_timesteps": 200, "num_updates": 40, "buffer_size": 10000, "update_epochs": 300, "update_policy_epochs": 100, "num_rollouts": 1, "num_envs": 1, "gamma": 0.9, "policy_lr_start": 0.007649592149703917, "policy_lr_end": 2.7271824981526242e-05, "q_lr_start": 0.013582391871765085, "q_lr_end": 0.0002058258115096068, "alpha": 0.6565128343323917, "eta": 3.3419695298808128, "autotune": false, "target_entropy_scale": 0.1, "linear_schedule": false, "__trial_index__": 2}, "time_since_restore": 23.443394422531128, "iterations_since_restore": 21}
{"reward": 21.0, "timestamp": 1711468831, "checkpoint_dir_name": null, "done": false, "training_iteration": 22, "trial_id": "5ed6c2ee", "date": "2024-03-26_17-00-31", "time_this_iter_s": 1.0913043022155762, "time_total_s": 24.534698724746704, "pid": 436, "hostname": "Nicolass-Air.technicolor.net", "node_ip": "127.0.0.1", "config": {"exp_name": "QREPS", "seed": 1, "torch_deterministic": true, "cuda": true, "track": false, "wandb_project_name": "QREPS_CartPole-v1", "wandb_entity": "TFG", "capture_video": false, "env_id": "CartPole-v1", "total_timesteps": 200, "num_updates": 40, "buffer_size": 10000, "update_epochs": 300, "update_policy_epochs": 100, "num_rollouts": 1, "num_envs": 1, "gamma": 0.9, "policy_lr_start": 0.007649592149703917, "policy_lr_end": 2.7271824981526242e-05, "q_lr_start": 0.013582391871765085, "q_lr_end": 0.0002058258115096068, "alpha": 0.6565128343323917, "eta": 3.3419695298808128, "autotune": false, "target_entropy_scale": 0.1, "linear_schedule": false, "__trial_index__": 2}, "time_since_restore": 24.534698724746704, "iterations_since_restore": 22}
{"reward": 21.0, "timestamp": 1711468832, "checkpoint_dir_name": null, "done": false, "training_iteration": 23, "trial_id": "5ed6c2ee", "date": "2024-03-26_17-00-32", "time_this_iter_s": 1.168915033340454, "time_total_s": 25.703613758087158, "pid": 436, "hostname": "Nicolass-Air.technicolor.net", "node_ip": "127.0.0.1", "config": {"exp_name": "QREPS", "seed": 1, "torch_deterministic": true, "cuda": true, "track": false, "wandb_project_name": "QREPS_CartPole-v1", "wandb_entity": "TFG", "capture_video": false, "env_id": "CartPole-v1", "total_timesteps": 200, "num_updates": 40, "buffer_size": 10000, "update_epochs": 300, "update_policy_epochs": 100, "num_rollouts": 1, "num_envs": 1, "gamma": 0.9, "policy_lr_start": 0.007649592149703917, "policy_lr_end": 2.7271824981526242e-05, "q_lr_start": 0.013582391871765085, "q_lr_end": 0.0002058258115096068, "alpha": 0.6565128343323917, "eta": 3.3419695298808128, "autotune": false, "target_entropy_scale": 0.1, "linear_schedule": false, "__trial_index__": 2}, "time_since_restore": 25.703613758087158, "iterations_since_restore": 23}
{"reward": 21.0, "timestamp": 1711468833, "checkpoint_dir_name": null, "done": false, "training_iteration": 24, "trial_id": "5ed6c2ee", "date": "2024-03-26_17-00-33", "time_this_iter_s": 1.0589931011199951, "time_total_s": 26.762606859207153, "pid": 436, "hostname": "Nicolass-Air.technicolor.net", "node_ip": "127.0.0.1", "config": {"exp_name": "QREPS", "seed": 1, "torch_deterministic": true, "cuda": true, "track": false, "wandb_project_name": "QREPS_CartPole-v1", "wandb_entity": "TFG", "capture_video": false, "env_id": "CartPole-v1", "total_timesteps": 200, "num_updates": 40, "buffer_size": 10000, "update_epochs": 300, "update_policy_epochs": 100, "num_rollouts": 1, "num_envs": 1, "gamma": 0.9, "policy_lr_start": 0.007649592149703917, "policy_lr_end": 2.7271824981526242e-05, "q_lr_start": 0.013582391871765085, "q_lr_end": 0.0002058258115096068, "alpha": 0.6565128343323917, "eta": 3.3419695298808128, "autotune": false, "target_entropy_scale": 0.1, "linear_schedule": false, "__trial_index__": 2}, "time_since_restore": 26.762606859207153, "iterations_since_restore": 24}
{"reward": 21.0, "timestamp": 1711468834, "checkpoint_dir_name": null, "done": false, "training_iteration": 25, "trial_id": "5ed6c2ee", "date": "2024-03-26_17-00-34", "time_this_iter_s": 1.1285841464996338, "time_total_s": 27.891191005706787, "pid": 436, "hostname": "Nicolass-Air.technicolor.net", "node_ip": "127.0.0.1", "config": {"exp_name": "QREPS", "seed": 1, "torch_deterministic": true, "cuda": true, "track": false, "wandb_project_name": "QREPS_CartPole-v1", "wandb_entity": "TFG", "capture_video": false, "env_id": "CartPole-v1", "total_timesteps": 200, "num_updates": 40, "buffer_size": 10000, "update_epochs": 300, "update_policy_epochs": 100, "num_rollouts": 1, "num_envs": 1, "gamma": 0.9, "policy_lr_start": 0.007649592149703917, "policy_lr_end": 2.7271824981526242e-05, "q_lr_start": 0.013582391871765085, "q_lr_end": 0.0002058258115096068, "alpha": 0.6565128343323917, "eta": 3.3419695298808128, "autotune": false, "target_entropy_scale": 0.1, "linear_schedule": false, "__trial_index__": 2}, "time_since_restore": 27.891191005706787, "iterations_since_restore": 25}
{"reward": 21.0, "timestamp": 1711468835, "checkpoint_dir_name": null, "done": false, "training_iteration": 26, "trial_id": "5ed6c2ee", "date": "2024-03-26_17-00-35", "time_this_iter_s": 1.0721189975738525, "time_total_s": 28.96331000328064, "pid": 436, "hostname": "Nicolass-Air.technicolor.net", "node_ip": "127.0.0.1", "config": {"exp_name": "QREPS", "seed": 1, "torch_deterministic": true, "cuda": true, "track": false, "wandb_project_name": "QREPS_CartPole-v1", "wandb_entity": "TFG", "capture_video": false, "env_id": "CartPole-v1", "total_timesteps": 200, "num_updates": 40, "buffer_size": 10000, "update_epochs": 300, "update_policy_epochs": 100, "num_rollouts": 1, "num_envs": 1, "gamma": 0.9, "policy_lr_start": 0.007649592149703917, "policy_lr_end": 2.7271824981526242e-05, "q_lr_start": 0.013582391871765085, "q_lr_end": 0.0002058258115096068, "alpha": 0.6565128343323917, "eta": 3.3419695298808128, "autotune": false, "target_entropy_scale": 0.1, "linear_schedule": false, "__trial_index__": 2}, "time_since_restore": 28.96331000328064, "iterations_since_restore": 26}
{"reward": 21.0, "timestamp": 1711468836, "checkpoint_dir_name": null, "done": false, "training_iteration": 27, "trial_id": "5ed6c2ee", "date": "2024-03-26_17-00-36", "time_this_iter_s": 1.0322771072387695, "time_total_s": 29.99558711051941, "pid": 436, "hostname": "Nicolass-Air.technicolor.net", "node_ip": "127.0.0.1", "config": {"exp_name": "QREPS", "seed": 1, "torch_deterministic": true, "cuda": true, "track": false, "wandb_project_name": "QREPS_CartPole-v1", "wandb_entity": "TFG", "capture_video": false, "env_id": "CartPole-v1", "total_timesteps": 200, "num_updates": 40, "buffer_size": 10000, "update_epochs": 300, "update_policy_epochs": 100, "num_rollouts": 1, "num_envs": 1, "gamma": 0.9, "policy_lr_start": 0.007649592149703917, "policy_lr_end": 2.7271824981526242e-05, "q_lr_start": 0.013582391871765085, "q_lr_end": 0.0002058258115096068, "alpha": 0.6565128343323917, "eta": 3.3419695298808128, "autotune": false, "target_entropy_scale": 0.1, "linear_schedule": false, "__trial_index__": 2}, "time_since_restore": 29.99558711051941, "iterations_since_restore": 27}
{"reward": 21.0, "timestamp": 1711468838, "checkpoint_dir_name": null, "done": false, "training_iteration": 28, "trial_id": "5ed6c2ee", "date": "2024-03-26_17-00-38", "time_this_iter_s": 1.0688629150390625, "time_total_s": 31.06445002555847, "pid": 436, "hostname": "Nicolass-Air.technicolor.net", "node_ip": "127.0.0.1", "config": {"exp_name": "QREPS", "seed": 1, "torch_deterministic": true, "cuda": true, "track": false, "wandb_project_name": "QREPS_CartPole-v1", "wandb_entity": "TFG", "capture_video": false, "env_id": "CartPole-v1", "total_timesteps": 200, "num_updates": 40, "buffer_size": 10000, "update_epochs": 300, "update_policy_epochs": 100, "num_rollouts": 1, "num_envs": 1, "gamma": 0.9, "policy_lr_start": 0.007649592149703917, "policy_lr_end": 2.7271824981526242e-05, "q_lr_start": 0.013582391871765085, "q_lr_end": 0.0002058258115096068, "alpha": 0.6565128343323917, "eta": 3.3419695298808128, "autotune": false, "target_entropy_scale": 0.1, "linear_schedule": false, "__trial_index__": 2}, "time_since_restore": 31.06445002555847, "iterations_since_restore": 28}
{"reward": 21.0, "timestamp": 1711468839, "checkpoint_dir_name": null, "done": false, "training_iteration": 29, "trial_id": "5ed6c2ee", "date": "2024-03-26_17-00-39", "time_this_iter_s": 1.0793259143829346, "time_total_s": 32.143775939941406, "pid": 436, "hostname": "Nicolass-Air.technicolor.net", "node_ip": "127.0.0.1", "config": {"exp_name": "QREPS", "seed": 1, "torch_deterministic": true, "cuda": true, "track": false, "wandb_project_name": "QREPS_CartPole-v1", "wandb_entity": "TFG", "capture_video": false, "env_id": "CartPole-v1", "total_timesteps": 200, "num_updates": 40, "buffer_size": 10000, "update_epochs": 300, "update_policy_epochs": 100, "num_rollouts": 1, "num_envs": 1, "gamma": 0.9, "policy_lr_start": 0.007649592149703917, "policy_lr_end": 2.7271824981526242e-05, "q_lr_start": 0.013582391871765085, "q_lr_end": 0.0002058258115096068, "alpha": 0.6565128343323917, "eta": 3.3419695298808128, "autotune": false, "target_entropy_scale": 0.1, "linear_schedule": false, "__trial_index__": 2}, "time_since_restore": 32.143775939941406, "iterations_since_restore": 29}
{"reward": 21.0, "timestamp": 1711468840, "checkpoint_dir_name": null, "done": false, "training_iteration": 30, "trial_id": "5ed6c2ee", "date": "2024-03-26_17-00-40", "time_this_iter_s": 1.1088838577270508, "time_total_s": 33.25265979766846, "pid": 436, "hostname": "Nicolass-Air.technicolor.net", "node_ip": "127.0.0.1", "config": {"exp_name": "QREPS", "seed": 1, "torch_deterministic": true, "cuda": true, "track": false, "wandb_project_name": "QREPS_CartPole-v1", "wandb_entity": "TFG", "capture_video": false, "env_id": "CartPole-v1", "total_timesteps": 200, "num_updates": 40, "buffer_size": 10000, "update_epochs": 300, "update_policy_epochs": 100, "num_rollouts": 1, "num_envs": 1, "gamma": 0.9, "policy_lr_start": 0.007649592149703917, "policy_lr_end": 2.7271824981526242e-05, "q_lr_start": 0.013582391871765085, "q_lr_end": 0.0002058258115096068, "alpha": 0.6565128343323917, "eta": 3.3419695298808128, "autotune": false, "target_entropy_scale": 0.1, "linear_schedule": false, "__trial_index__": 2}, "time_since_restore": 33.25265979766846, "iterations_since_restore": 30}
{"reward": 21.0, "timestamp": 1711468841, "checkpoint_dir_name": null, "done": false, "training_iteration": 31, "trial_id": "5ed6c2ee", "date": "2024-03-26_17-00-41", "time_this_iter_s": 1.0725831985473633, "time_total_s": 34.32524299621582, "pid": 436, "hostname": "Nicolass-Air.technicolor.net", "node_ip": "127.0.0.1", "config": {"exp_name": "QREPS", "seed": 1, "torch_deterministic": true, "cuda": true, "track": false, "wandb_project_name": "QREPS_CartPole-v1", "wandb_entity": "TFG", "capture_video": false, "env_id": "CartPole-v1", "total_timesteps": 200, "num_updates": 40, "buffer_size": 10000, "update_epochs": 300, "update_policy_epochs": 100, "num_rollouts": 1, "num_envs": 1, "gamma": 0.9, "policy_lr_start": 0.007649592149703917, "policy_lr_end": 2.7271824981526242e-05, "q_lr_start": 0.013582391871765085, "q_lr_end": 0.0002058258115096068, "alpha": 0.6565128343323917, "eta": 3.3419695298808128, "autotune": false, "target_entropy_scale": 0.1, "linear_schedule": false, "__trial_index__": 2}, "time_since_restore": 34.32524299621582, "iterations_since_restore": 31}
{"reward": 21.0, "timestamp": 1711468842, "checkpoint_dir_name": null, "done": false, "training_iteration": 32, "trial_id": "5ed6c2ee", "date": "2024-03-26_17-00-42", "time_this_iter_s": 1.2318861484527588, "time_total_s": 35.55712914466858, "pid": 436, "hostname": "Nicolass-Air.technicolor.net", "node_ip": "127.0.0.1", "config": {"exp_name": "QREPS", "seed": 1, "torch_deterministic": true, "cuda": true, "track": false, "wandb_project_name": "QREPS_CartPole-v1", "wandb_entity": "TFG", "capture_video": false, "env_id": "CartPole-v1", "total_timesteps": 200, "num_updates": 40, "buffer_size": 10000, "update_epochs": 300, "update_policy_epochs": 100, "num_rollouts": 1, "num_envs": 1, "gamma": 0.9, "policy_lr_start": 0.007649592149703917, "policy_lr_end": 2.7271824981526242e-05, "q_lr_start": 0.013582391871765085, "q_lr_end": 0.0002058258115096068, "alpha": 0.6565128343323917, "eta": 3.3419695298808128, "autotune": false, "target_entropy_scale": 0.1, "linear_schedule": false, "__trial_index__": 2}, "time_since_restore": 35.55712914466858, "iterations_since_restore": 32}
{"reward": 21.0, "timestamp": 1711468843, "checkpoint_dir_name": null, "done": false, "training_iteration": 33, "trial_id": "5ed6c2ee", "date": "2024-03-26_17-00-43", "time_this_iter_s": 1.1692020893096924, "time_total_s": 36.72633123397827, "pid": 436, "hostname": "Nicolass-Air.technicolor.net", "node_ip": "127.0.0.1", "config": {"exp_name": "QREPS", "seed": 1, "torch_deterministic": true, "cuda": true, "track": false, "wandb_project_name": "QREPS_CartPole-v1", "wandb_entity": "TFG", "capture_video": false, "env_id": "CartPole-v1", "total_timesteps": 200, "num_updates": 40, "buffer_size": 10000, "update_epochs": 300, "update_policy_epochs": 100, "num_rollouts": 1, "num_envs": 1, "gamma": 0.9, "policy_lr_start": 0.007649592149703917, "policy_lr_end": 2.7271824981526242e-05, "q_lr_start": 0.013582391871765085, "q_lr_end": 0.0002058258115096068, "alpha": 0.6565128343323917, "eta": 3.3419695298808128, "autotune": false, "target_entropy_scale": 0.1, "linear_schedule": false, "__trial_index__": 2}, "time_since_restore": 36.72633123397827, "iterations_since_restore": 33}
{"reward": 21.0, "timestamp": 1711468844, "checkpoint_dir_name": null, "done": false, "training_iteration": 34, "trial_id": "5ed6c2ee", "date": "2024-03-26_17-00-44", "time_this_iter_s": 1.2041571140289307, "time_total_s": 37.9304883480072, "pid": 436, "hostname": "Nicolass-Air.technicolor.net", "node_ip": "127.0.0.1", "config": {"exp_name": "QREPS", "seed": 1, "torch_deterministic": true, "cuda": true, "track": false, "wandb_project_name": "QREPS_CartPole-v1", "wandb_entity": "TFG", "capture_video": false, "env_id": "CartPole-v1", "total_timesteps": 200, "num_updates": 40, "buffer_size": 10000, "update_epochs": 300, "update_policy_epochs": 100, "num_rollouts": 1, "num_envs": 1, "gamma": 0.9, "policy_lr_start": 0.007649592149703917, "policy_lr_end": 2.7271824981526242e-05, "q_lr_start": 0.013582391871765085, "q_lr_end": 0.0002058258115096068, "alpha": 0.6565128343323917, "eta": 3.3419695298808128, "autotune": false, "target_entropy_scale": 0.1, "linear_schedule": false, "__trial_index__": 2}, "time_since_restore": 37.9304883480072, "iterations_since_restore": 34}
{"reward": 21.0, "timestamp": 1711468846, "checkpoint_dir_name": null, "done": false, "training_iteration": 35, "trial_id": "5ed6c2ee", "date": "2024-03-26_17-00-46", "time_this_iter_s": 1.0733191967010498, "time_total_s": 39.00380754470825, "pid": 436, "hostname": "Nicolass-Air.technicolor.net", "node_ip": "127.0.0.1", "config": {"exp_name": "QREPS", "seed": 1, "torch_deterministic": true, "cuda": true, "track": false, "wandb_project_name": "QREPS_CartPole-v1", "wandb_entity": "TFG", "capture_video": false, "env_id": "CartPole-v1", "total_timesteps": 200, "num_updates": 40, "buffer_size": 10000, "update_epochs": 300, "update_policy_epochs": 100, "num_rollouts": 1, "num_envs": 1, "gamma": 0.9, "policy_lr_start": 0.007649592149703917, "policy_lr_end": 2.7271824981526242e-05, "q_lr_start": 0.013582391871765085, "q_lr_end": 0.0002058258115096068, "alpha": 0.6565128343323917, "eta": 3.3419695298808128, "autotune": false, "target_entropy_scale": 0.1, "linear_schedule": false, "__trial_index__": 2}, "time_since_restore": 39.00380754470825, "iterations_since_restore": 35}
{"reward": 21.0, "timestamp": 1711468847, "checkpoint_dir_name": null, "done": false, "training_iteration": 36, "trial_id": "5ed6c2ee", "date": "2024-03-26_17-00-47", "time_this_iter_s": 1.078629732131958, "time_total_s": 40.08243727684021, "pid": 436, "hostname": "Nicolass-Air.technicolor.net", "node_ip": "127.0.0.1", "config": {"exp_name": "QREPS", "seed": 1, "torch_deterministic": true, "cuda": true, "track": false, "wandb_project_name": "QREPS_CartPole-v1", "wandb_entity": "TFG", "capture_video": false, "env_id": "CartPole-v1", "total_timesteps": 200, "num_updates": 40, "buffer_size": 10000, "update_epochs": 300, "update_policy_epochs": 100, "num_rollouts": 1, "num_envs": 1, "gamma": 0.9, "policy_lr_start": 0.007649592149703917, "policy_lr_end": 2.7271824981526242e-05, "q_lr_start": 0.013582391871765085, "q_lr_end": 0.0002058258115096068, "alpha": 0.6565128343323917, "eta": 3.3419695298808128, "autotune": false, "target_entropy_scale": 0.1, "linear_schedule": false, "__trial_index__": 2}, "time_since_restore": 40.08243727684021, "iterations_since_restore": 36}
{"reward": 21.0, "timestamp": 1711468848, "checkpoint_dir_name": null, "done": false, "training_iteration": 37, "trial_id": "5ed6c2ee", "date": "2024-03-26_17-00-48", "time_this_iter_s": 1.075958013534546, "time_total_s": 41.158395290374756, "pid": 436, "hostname": "Nicolass-Air.technicolor.net", "node_ip": "127.0.0.1", "config": {"exp_name": "QREPS", "seed": 1, "torch_deterministic": true, "cuda": true, "track": false, "wandb_project_name": "QREPS_CartPole-v1", "wandb_entity": "TFG", "capture_video": false, "env_id": "CartPole-v1", "total_timesteps": 200, "num_updates": 40, "buffer_size": 10000, "update_epochs": 300, "update_policy_epochs": 100, "num_rollouts": 1, "num_envs": 1, "gamma": 0.9, "policy_lr_start": 0.007649592149703917, "policy_lr_end": 2.7271824981526242e-05, "q_lr_start": 0.013582391871765085, "q_lr_end": 0.0002058258115096068, "alpha": 0.6565128343323917, "eta": 3.3419695298808128, "autotune": false, "target_entropy_scale": 0.1, "linear_schedule": false, "__trial_index__": 2}, "time_since_restore": 41.158395290374756, "iterations_since_restore": 37}
{"reward": 21.0, "timestamp": 1711468849, "checkpoint_dir_name": null, "done": false, "training_iteration": 38, "trial_id": "5ed6c2ee", "date": "2024-03-26_17-00-49", "time_this_iter_s": 1.0991129875183105, "time_total_s": 42.257508277893066, "pid": 436, "hostname": "Nicolass-Air.technicolor.net", "node_ip": "127.0.0.1", "config": {"exp_name": "QREPS", "seed": 1, "torch_deterministic": true, "cuda": true, "track": false, "wandb_project_name": "QREPS_CartPole-v1", "wandb_entity": "TFG", "capture_video": false, "env_id": "CartPole-v1", "total_timesteps": 200, "num_updates": 40, "buffer_size": 10000, "update_epochs": 300, "update_policy_epochs": 100, "num_rollouts": 1, "num_envs": 1, "gamma": 0.9, "policy_lr_start": 0.007649592149703917, "policy_lr_end": 2.7271824981526242e-05, "q_lr_start": 0.013582391871765085, "q_lr_end": 0.0002058258115096068, "alpha": 0.6565128343323917, "eta": 3.3419695298808128, "autotune": false, "target_entropy_scale": 0.1, "linear_schedule": false, "__trial_index__": 2}, "time_since_restore": 42.257508277893066, "iterations_since_restore": 38}
{"reward": 21.0, "timestamp": 1711468850, "checkpoint_dir_name": null, "done": false, "training_iteration": 39, "trial_id": "5ed6c2ee", "date": "2024-03-26_17-00-50", "time_this_iter_s": 1.0132198333740234, "time_total_s": 43.27072811126709, "pid": 436, "hostname": "Nicolass-Air.technicolor.net", "node_ip": "127.0.0.1", "config": {"exp_name": "QREPS", "seed": 1, "torch_deterministic": true, "cuda": true, "track": false, "wandb_project_name": "QREPS_CartPole-v1", "wandb_entity": "TFG", "capture_video": false, "env_id": "CartPole-v1", "total_timesteps": 200, "num_updates": 40, "buffer_size": 10000, "update_epochs": 300, "update_policy_epochs": 100, "num_rollouts": 1, "num_envs": 1, "gamma": 0.9, "policy_lr_start": 0.007649592149703917, "policy_lr_end": 2.7271824981526242e-05, "q_lr_start": 0.013582391871765085, "q_lr_end": 0.0002058258115096068, "alpha": 0.6565128343323917, "eta": 3.3419695298808128, "autotune": false, "target_entropy_scale": 0.1, "linear_schedule": false, "__trial_index__": 2}, "time_since_restore": 43.27072811126709, "iterations_since_restore": 39}
{"reward": 21.0, "timestamp": 1711468851, "checkpoint_dir_name": null, "done": false, "training_iteration": 40, "trial_id": "5ed6c2ee", "date": "2024-03-26_17-00-51", "time_this_iter_s": 1.0153541564941406, "time_total_s": 44.28608226776123, "pid": 436, "hostname": "Nicolass-Air.technicolor.net", "node_ip": "127.0.0.1", "config": {"exp_name": "QREPS", "seed": 1, "torch_deterministic": true, "cuda": true, "track": false, "wandb_project_name": "QREPS_CartPole-v1", "wandb_entity": "TFG", "capture_video": false, "env_id": "CartPole-v1", "total_timesteps": 200, "num_updates": 40, "buffer_size": 10000, "update_epochs": 300, "update_policy_epochs": 100, "num_rollouts": 1, "num_envs": 1, "gamma": 0.9, "policy_lr_start": 0.007649592149703917, "policy_lr_end": 2.7271824981526242e-05, "q_lr_start": 0.013582391871765085, "q_lr_end": 0.0002058258115096068, "alpha": 0.6565128343323917, "eta": 3.3419695298808128, "autotune": false, "target_entropy_scale": 0.1, "linear_schedule": false, "__trial_index__": 2}, "time_since_restore": 44.28608226776123, "iterations_since_restore": 40}
