{"reward": 14.875, "timestamp": 1711475007, "checkpoint_dir_name": null, "done": false, "training_iteration": 1, "trial_id": "a29fb57c", "date": "2024-03-26_18-43-27", "time_this_iter_s": 3.159133195877075, "time_total_s": 3.159133195877075, "pid": 5327, "hostname": "Nicolass-Air.technicolor.net", "node_ip": "127.0.0.1", "config": {"exp_name": "QREPS", "seed": 1, "torch_deterministic": true, "cuda": true, "track": false, "wandb_project_name": "QREPS_CartPole-v1", "wandb_entity": "TFG", "capture_video": false, "env_id": "CartPole-v1", "total_timesteps": 500, "num_updates": 70, "buffer_size": 10000, "update_epochs": 10, "update_policy_epochs": 450, "num_rollouts": 8, "num_envs": 2, "gamma": 1, "policy_lr_start": 0.06548824413400488, "policy_lr_end": 0.0004704992874039154, "q_lr_start": 0.0517363360590694, "q_lr_end": 5.172503184677546e-05, "alpha": 0.6380395140274236, "eta": 1.379141379818223, "autotune": false, "target_entropy_scale": 0.1, "linear_schedule": false, "__trial_index__": 1}, "time_since_restore": 3.159133195877075, "iterations_since_restore": 1}
{"reward": 10.5, "timestamp": 1711475010, "checkpoint_dir_name": null, "done": false, "training_iteration": 2, "trial_id": "a29fb57c", "date": "2024-03-26_18-43-30", "time_this_iter_s": 2.950813055038452, "time_total_s": 6.109946250915527, "pid": 5327, "hostname": "Nicolass-Air.technicolor.net", "node_ip": "127.0.0.1", "config": {"exp_name": "QREPS", "seed": 1, "torch_deterministic": true, "cuda": true, "track": false, "wandb_project_name": "QREPS_CartPole-v1", "wandb_entity": "TFG", "capture_video": false, "env_id": "CartPole-v1", "total_timesteps": 500, "num_updates": 70, "buffer_size": 10000, "update_epochs": 10, "update_policy_epochs": 450, "num_rollouts": 8, "num_envs": 2, "gamma": 1, "policy_lr_start": 0.06548824413400488, "policy_lr_end": 0.0004704992874039154, "q_lr_start": 0.0517363360590694, "q_lr_end": 5.172503184677546e-05, "alpha": 0.6380395140274236, "eta": 1.379141379818223, "autotune": false, "target_entropy_scale": 0.1, "linear_schedule": false, "__trial_index__": 1}, "time_since_restore": 6.109946250915527, "iterations_since_restore": 2}
{"reward": 10.0, "timestamp": 1711475013, "checkpoint_dir_name": null, "done": false, "training_iteration": 3, "trial_id": "a29fb57c", "date": "2024-03-26_18-43-33", "time_this_iter_s": 2.5731868743896484, "time_total_s": 8.683133125305176, "pid": 5327, "hostname": "Nicolass-Air.technicolor.net", "node_ip": "127.0.0.1", "config": {"exp_name": "QREPS", "seed": 1, "torch_deterministic": true, "cuda": true, "track": false, "wandb_project_name": "QREPS_CartPole-v1", "wandb_entity": "TFG", "capture_video": false, "env_id": "CartPole-v1", "total_timesteps": 500, "num_updates": 70, "buffer_size": 10000, "update_epochs": 10, "update_policy_epochs": 450, "num_rollouts": 8, "num_envs": 2, "gamma": 1, "policy_lr_start": 0.06548824413400488, "policy_lr_end": 0.0004704992874039154, "q_lr_start": 0.0517363360590694, "q_lr_end": 5.172503184677546e-05, "alpha": 0.6380395140274236, "eta": 1.379141379818223, "autotune": false, "target_entropy_scale": 0.1, "linear_schedule": false, "__trial_index__": 1}, "time_since_restore": 8.683133125305176, "iterations_since_restore": 3}
{"reward": 9.75, "timestamp": 1711475015, "checkpoint_dir_name": null, "done": false, "training_iteration": 4, "trial_id": "a29fb57c", "date": "2024-03-26_18-43-35", "time_this_iter_s": 2.6849539279937744, "time_total_s": 11.36808705329895, "pid": 5327, "hostname": "Nicolass-Air.technicolor.net", "node_ip": "127.0.0.1", "config": {"exp_name": "QREPS", "seed": 1, "torch_deterministic": true, "cuda": true, "track": false, "wandb_project_name": "QREPS_CartPole-v1", "wandb_entity": "TFG", "capture_video": false, "env_id": "CartPole-v1", "total_timesteps": 500, "num_updates": 70, "buffer_size": 10000, "update_epochs": 10, "update_policy_epochs": 450, "num_rollouts": 8, "num_envs": 2, "gamma": 1, "policy_lr_start": 0.06548824413400488, "policy_lr_end": 0.0004704992874039154, "q_lr_start": 0.0517363360590694, "q_lr_end": 5.172503184677546e-05, "alpha": 0.6380395140274236, "eta": 1.379141379818223, "autotune": false, "target_entropy_scale": 0.1, "linear_schedule": false, "__trial_index__": 1}, "time_since_restore": 11.36808705329895, "iterations_since_restore": 4}
{"reward": 9.375, "timestamp": 1711475018, "checkpoint_dir_name": null, "done": false, "training_iteration": 5, "trial_id": "a29fb57c", "date": "2024-03-26_18-43-38", "time_this_iter_s": 2.7452139854431152, "time_total_s": 14.113301038742065, "pid": 5327, "hostname": "Nicolass-Air.technicolor.net", "node_ip": "127.0.0.1", "config": {"exp_name": "QREPS", "seed": 1, "torch_deterministic": true, "cuda": true, "track": false, "wandb_project_name": "QREPS_CartPole-v1", "wandb_entity": "TFG", "capture_video": false, "env_id": "CartPole-v1", "total_timesteps": 500, "num_updates": 70, "buffer_size": 10000, "update_epochs": 10, "update_policy_epochs": 450, "num_rollouts": 8, "num_envs": 2, "gamma": 1, "policy_lr_start": 0.06548824413400488, "policy_lr_end": 0.0004704992874039154, "q_lr_start": 0.0517363360590694, "q_lr_end": 5.172503184677546e-05, "alpha": 0.6380395140274236, "eta": 1.379141379818223, "autotune": false, "target_entropy_scale": 0.1, "linear_schedule": false, "__trial_index__": 1}, "time_since_restore": 14.113301038742065, "iterations_since_restore": 5}
{"reward": 9.375, "timestamp": 1711475021, "checkpoint_dir_name": null, "done": false, "training_iteration": 6, "trial_id": "a29fb57c", "date": "2024-03-26_18-43-41", "time_this_iter_s": 2.963844060897827, "time_total_s": 17.077145099639893, "pid": 5327, "hostname": "Nicolass-Air.technicolor.net", "node_ip": "127.0.0.1", "config": {"exp_name": "QREPS", "seed": 1, "torch_deterministic": true, "cuda": true, "track": false, "wandb_project_name": "QREPS_CartPole-v1", "wandb_entity": "TFG", "capture_video": false, "env_id": "CartPole-v1", "total_timesteps": 500, "num_updates": 70, "buffer_size": 10000, "update_epochs": 10, "update_policy_epochs": 450, "num_rollouts": 8, "num_envs": 2, "gamma": 1, "policy_lr_start": 0.06548824413400488, "policy_lr_end": 0.0004704992874039154, "q_lr_start": 0.0517363360590694, "q_lr_end": 5.172503184677546e-05, "alpha": 0.6380395140274236, "eta": 1.379141379818223, "autotune": false, "target_entropy_scale": 0.1, "linear_schedule": false, "__trial_index__": 1}, "time_since_restore": 17.077145099639893, "iterations_since_restore": 6}
{"reward": 9.125, "timestamp": 1711475024, "checkpoint_dir_name": null, "done": false, "training_iteration": 7, "trial_id": "a29fb57c", "date": "2024-03-26_18-43-44", "time_this_iter_s": 2.583836793899536, "time_total_s": 19.66098189353943, "pid": 5327, "hostname": "Nicolass-Air.technicolor.net", "node_ip": "127.0.0.1", "config": {"exp_name": "QREPS", "seed": 1, "torch_deterministic": true, "cuda": true, "track": false, "wandb_project_name": "QREPS_CartPole-v1", "wandb_entity": "TFG", "capture_video": false, "env_id": "CartPole-v1", "total_timesteps": 500, "num_updates": 70, "buffer_size": 10000, "update_epochs": 10, "update_policy_epochs": 450, "num_rollouts": 8, "num_envs": 2, "gamma": 1, "policy_lr_start": 0.06548824413400488, "policy_lr_end": 0.0004704992874039154, "q_lr_start": 0.0517363360590694, "q_lr_end": 5.172503184677546e-05, "alpha": 0.6380395140274236, "eta": 1.379141379818223, "autotune": false, "target_entropy_scale": 0.1, "linear_schedule": false, "__trial_index__": 1}, "time_since_restore": 19.66098189353943, "iterations_since_restore": 7}
{"reward": 9.125, "timestamp": 1711475026, "checkpoint_dir_name": null, "done": false, "training_iteration": 8, "trial_id": "a29fb57c", "date": "2024-03-26_18-43-46", "time_this_iter_s": 2.551610231399536, "time_total_s": 22.212592124938965, "pid": 5327, "hostname": "Nicolass-Air.technicolor.net", "node_ip": "127.0.0.1", "config": {"exp_name": "QREPS", "seed": 1, "torch_deterministic": true, "cuda": true, "track": false, "wandb_project_name": "QREPS_CartPole-v1", "wandb_entity": "TFG", "capture_video": false, "env_id": "CartPole-v1", "total_timesteps": 500, "num_updates": 70, "buffer_size": 10000, "update_epochs": 10, "update_policy_epochs": 450, "num_rollouts": 8, "num_envs": 2, "gamma": 1, "policy_lr_start": 0.06548824413400488, "policy_lr_end": 0.0004704992874039154, "q_lr_start": 0.0517363360590694, "q_lr_end": 5.172503184677546e-05, "alpha": 0.6380395140274236, "eta": 1.379141379818223, "autotune": false, "target_entropy_scale": 0.1, "linear_schedule": false, "__trial_index__": 1}, "time_since_restore": 22.212592124938965, "iterations_since_restore": 8}
{"reward": 9.0, "timestamp": 1711475029, "checkpoint_dir_name": null, "done": false, "training_iteration": 9, "trial_id": "a29fb57c", "date": "2024-03-26_18-43-49", "time_this_iter_s": 2.831076145172119, "time_total_s": 25.043668270111084, "pid": 5327, "hostname": "Nicolass-Air.technicolor.net", "node_ip": "127.0.0.1", "config": {"exp_name": "QREPS", "seed": 1, "torch_deterministic": true, "cuda": true, "track": false, "wandb_project_name": "QREPS_CartPole-v1", "wandb_entity": "TFG", "capture_video": false, "env_id": "CartPole-v1", "total_timesteps": 500, "num_updates": 70, "buffer_size": 10000, "update_epochs": 10, "update_policy_epochs": 450, "num_rollouts": 8, "num_envs": 2, "gamma": 1, "policy_lr_start": 0.06548824413400488, "policy_lr_end": 0.0004704992874039154, "q_lr_start": 0.0517363360590694, "q_lr_end": 5.172503184677546e-05, "alpha": 0.6380395140274236, "eta": 1.379141379818223, "autotune": false, "target_entropy_scale": 0.1, "linear_schedule": false, "__trial_index__": 1}, "time_since_restore": 25.043668270111084, "iterations_since_restore": 9}
{"reward": 9.0, "timestamp": 1711475031, "checkpoint_dir_name": null, "done": false, "training_iteration": 10, "trial_id": "a29fb57c", "date": "2024-03-26_18-43-51", "time_this_iter_s": 2.4346110820770264, "time_total_s": 27.47827935218811, "pid": 5327, "hostname": "Nicolass-Air.technicolor.net", "node_ip": "127.0.0.1", "config": {"exp_name": "QREPS", "seed": 1, "torch_deterministic": true, "cuda": true, "track": false, "wandb_project_name": "QREPS_CartPole-v1", "wandb_entity": "TFG", "capture_video": false, "env_id": "CartPole-v1", "total_timesteps": 500, "num_updates": 70, "buffer_size": 10000, "update_epochs": 10, "update_policy_epochs": 450, "num_rollouts": 8, "num_envs": 2, "gamma": 1, "policy_lr_start": 0.06548824413400488, "policy_lr_end": 0.0004704992874039154, "q_lr_start": 0.0517363360590694, "q_lr_end": 5.172503184677546e-05, "alpha": 0.6380395140274236, "eta": 1.379141379818223, "autotune": false, "target_entropy_scale": 0.1, "linear_schedule": false, "__trial_index__": 1}, "time_since_restore": 27.47827935218811, "iterations_since_restore": 10}
{"reward": 9.125, "timestamp": 1711475034, "checkpoint_dir_name": null, "done": false, "training_iteration": 11, "trial_id": "a29fb57c", "date": "2024-03-26_18-43-54", "time_this_iter_s": 2.104281187057495, "time_total_s": 29.582560539245605, "pid": 5327, "hostname": "Nicolass-Air.technicolor.net", "node_ip": "127.0.0.1", "config": {"exp_name": "QREPS", "seed": 1, "torch_deterministic": true, "cuda": true, "track": false, "wandb_project_name": "QREPS_CartPole-v1", "wandb_entity": "TFG", "capture_video": false, "env_id": "CartPole-v1", "total_timesteps": 500, "num_updates": 70, "buffer_size": 10000, "update_epochs": 10, "update_policy_epochs": 450, "num_rollouts": 8, "num_envs": 2, "gamma": 1, "policy_lr_start": 0.06548824413400488, "policy_lr_end": 0.0004704992874039154, "q_lr_start": 0.0517363360590694, "q_lr_end": 5.172503184677546e-05, "alpha": 0.6380395140274236, "eta": 1.379141379818223, "autotune": false, "target_entropy_scale": 0.1, "linear_schedule": false, "__trial_index__": 1}, "time_since_restore": 29.582560539245605, "iterations_since_restore": 11}
{"reward": 9.0, "timestamp": 1711475036, "checkpoint_dir_name": null, "done": false, "training_iteration": 12, "trial_id": "a29fb57c", "date": "2024-03-26_18-43-56", "time_this_iter_s": 2.255535125732422, "time_total_s": 31.838095664978027, "pid": 5327, "hostname": "Nicolass-Air.technicolor.net", "node_ip": "127.0.0.1", "config": {"exp_name": "QREPS", "seed": 1, "torch_deterministic": true, "cuda": true, "track": false, "wandb_project_name": "QREPS_CartPole-v1", "wandb_entity": "TFG", "capture_video": false, "env_id": "CartPole-v1", "total_timesteps": 500, "num_updates": 70, "buffer_size": 10000, "update_epochs": 10, "update_policy_epochs": 450, "num_rollouts": 8, "num_envs": 2, "gamma": 1, "policy_lr_start": 0.06548824413400488, "policy_lr_end": 0.0004704992874039154, "q_lr_start": 0.0517363360590694, "q_lr_end": 5.172503184677546e-05, "alpha": 0.6380395140274236, "eta": 1.379141379818223, "autotune": false, "target_entropy_scale": 0.1, "linear_schedule": false, "__trial_index__": 1}, "time_since_restore": 31.838095664978027, "iterations_since_restore": 12}
{"reward": 9.0, "timestamp": 1711475038, "checkpoint_dir_name": null, "done": false, "training_iteration": 13, "trial_id": "a29fb57c", "date": "2024-03-26_18-43-58", "time_this_iter_s": 2.2308270931243896, "time_total_s": 34.06892275810242, "pid": 5327, "hostname": "Nicolass-Air.technicolor.net", "node_ip": "127.0.0.1", "config": {"exp_name": "QREPS", "seed": 1, "torch_deterministic": true, "cuda": true, "track": false, "wandb_project_name": "QREPS_CartPole-v1", "wandb_entity": "TFG", "capture_video": false, "env_id": "CartPole-v1", "total_timesteps": 500, "num_updates": 70, "buffer_size": 10000, "update_epochs": 10, "update_policy_epochs": 450, "num_rollouts": 8, "num_envs": 2, "gamma": 1, "policy_lr_start": 0.06548824413400488, "policy_lr_end": 0.0004704992874039154, "q_lr_start": 0.0517363360590694, "q_lr_end": 5.172503184677546e-05, "alpha": 0.6380395140274236, "eta": 1.379141379818223, "autotune": false, "target_entropy_scale": 0.1, "linear_schedule": false, "__trial_index__": 1}, "time_since_restore": 34.06892275810242, "iterations_since_restore": 13}
{"reward": 9.0, "timestamp": 1711475040, "checkpoint_dir_name": null, "done": false, "training_iteration": 14, "trial_id": "a29fb57c", "date": "2024-03-26_18-44-00", "time_this_iter_s": 2.3760788440704346, "time_total_s": 36.44500160217285, "pid": 5327, "hostname": "Nicolass-Air.technicolor.net", "node_ip": "127.0.0.1", "config": {"exp_name": "QREPS", "seed": 1, "torch_deterministic": true, "cuda": true, "track": false, "wandb_project_name": "QREPS_CartPole-v1", "wandb_entity": "TFG", "capture_video": false, "env_id": "CartPole-v1", "total_timesteps": 500, "num_updates": 70, "buffer_size": 10000, "update_epochs": 10, "update_policy_epochs": 450, "num_rollouts": 8, "num_envs": 2, "gamma": 1, "policy_lr_start": 0.06548824413400488, "policy_lr_end": 0.0004704992874039154, "q_lr_start": 0.0517363360590694, "q_lr_end": 5.172503184677546e-05, "alpha": 0.6380395140274236, "eta": 1.379141379818223, "autotune": false, "target_entropy_scale": 0.1, "linear_schedule": false, "__trial_index__": 1}, "time_since_restore": 36.44500160217285, "iterations_since_restore": 14}
{"reward": 9.0, "timestamp": 1711475043, "checkpoint_dir_name": null, "done": false, "training_iteration": 15, "trial_id": "a29fb57c", "date": "2024-03-26_18-44-03", "time_this_iter_s": 2.471552610397339, "time_total_s": 38.91655421257019, "pid": 5327, "hostname": "Nicolass-Air.technicolor.net", "node_ip": "127.0.0.1", "config": {"exp_name": "QREPS", "seed": 1, "torch_deterministic": true, "cuda": true, "track": false, "wandb_project_name": "QREPS_CartPole-v1", "wandb_entity": "TFG", "capture_video": false, "env_id": "CartPole-v1", "total_timesteps": 500, "num_updates": 70, "buffer_size": 10000, "update_epochs": 10, "update_policy_epochs": 450, "num_rollouts": 8, "num_envs": 2, "gamma": 1, "policy_lr_start": 0.06548824413400488, "policy_lr_end": 0.0004704992874039154, "q_lr_start": 0.0517363360590694, "q_lr_end": 5.172503184677546e-05, "alpha": 0.6380395140274236, "eta": 1.379141379818223, "autotune": false, "target_entropy_scale": 0.1, "linear_schedule": false, "__trial_index__": 1}, "time_since_restore": 38.91655421257019, "iterations_since_restore": 15}
{"reward": 9.0, "timestamp": 1711475046, "checkpoint_dir_name": null, "done": false, "training_iteration": 16, "trial_id": "a29fb57c", "date": "2024-03-26_18-44-06", "time_this_iter_s": 2.6701669692993164, "time_total_s": 41.58672118186951, "pid": 5327, "hostname": "Nicolass-Air.technicolor.net", "node_ip": "127.0.0.1", "config": {"exp_name": "QREPS", "seed": 1, "torch_deterministic": true, "cuda": true, "track": false, "wandb_project_name": "QREPS_CartPole-v1", "wandb_entity": "TFG", "capture_video": false, "env_id": "CartPole-v1", "total_timesteps": 500, "num_updates": 70, "buffer_size": 10000, "update_epochs": 10, "update_policy_epochs": 450, "num_rollouts": 8, "num_envs": 2, "gamma": 1, "policy_lr_start": 0.06548824413400488, "policy_lr_end": 0.0004704992874039154, "q_lr_start": 0.0517363360590694, "q_lr_end": 5.172503184677546e-05, "alpha": 0.6380395140274236, "eta": 1.379141379818223, "autotune": false, "target_entropy_scale": 0.1, "linear_schedule": false, "__trial_index__": 1}, "time_since_restore": 41.58672118186951, "iterations_since_restore": 16}
{"reward": 9.0, "timestamp": 1711475048, "checkpoint_dir_name": null, "done": false, "training_iteration": 17, "trial_id": "a29fb57c", "date": "2024-03-26_18-44-08", "time_this_iter_s": 2.3874690532684326, "time_total_s": 43.97419023513794, "pid": 5327, "hostname": "Nicolass-Air.technicolor.net", "node_ip": "127.0.0.1", "config": {"exp_name": "QREPS", "seed": 1, "torch_deterministic": true, "cuda": true, "track": false, "wandb_project_name": "QREPS_CartPole-v1", "wandb_entity": "TFG", "capture_video": false, "env_id": "CartPole-v1", "total_timesteps": 500, "num_updates": 70, "buffer_size": 10000, "update_epochs": 10, "update_policy_epochs": 450, "num_rollouts": 8, "num_envs": 2, "gamma": 1, "policy_lr_start": 0.06548824413400488, "policy_lr_end": 0.0004704992874039154, "q_lr_start": 0.0517363360590694, "q_lr_end": 5.172503184677546e-05, "alpha": 0.6380395140274236, "eta": 1.379141379818223, "autotune": false, "target_entropy_scale": 0.1, "linear_schedule": false, "__trial_index__": 1}, "time_since_restore": 43.97419023513794, "iterations_since_restore": 17}
{"reward": 9.0, "timestamp": 1711475050, "checkpoint_dir_name": null, "done": false, "training_iteration": 18, "trial_id": "a29fb57c", "date": "2024-03-26_18-44-10", "time_this_iter_s": 2.0890650749206543, "time_total_s": 46.063255310058594, "pid": 5327, "hostname": "Nicolass-Air.technicolor.net", "node_ip": "127.0.0.1", "config": {"exp_name": "QREPS", "seed": 1, "torch_deterministic": true, "cuda": true, "track": false, "wandb_project_name": "QREPS_CartPole-v1", "wandb_entity": "TFG", "capture_video": false, "env_id": "CartPole-v1", "total_timesteps": 500, "num_updates": 70, "buffer_size": 10000, "update_epochs": 10, "update_policy_epochs": 450, "num_rollouts": 8, "num_envs": 2, "gamma": 1, "policy_lr_start": 0.06548824413400488, "policy_lr_end": 0.0004704992874039154, "q_lr_start": 0.0517363360590694, "q_lr_end": 5.172503184677546e-05, "alpha": 0.6380395140274236, "eta": 1.379141379818223, "autotune": false, "target_entropy_scale": 0.1, "linear_schedule": false, "__trial_index__": 1}, "time_since_restore": 46.063255310058594, "iterations_since_restore": 18}
{"reward": 9.0, "timestamp": 1711475053, "checkpoint_dir_name": null, "done": false, "training_iteration": 19, "trial_id": "a29fb57c", "date": "2024-03-26_18-44-13", "time_this_iter_s": 2.995194911956787, "time_total_s": 49.05845022201538, "pid": 5327, "hostname": "Nicolass-Air.technicolor.net", "node_ip": "127.0.0.1", "config": {"exp_name": "QREPS", "seed": 1, "torch_deterministic": true, "cuda": true, "track": false, "wandb_project_name": "QREPS_CartPole-v1", "wandb_entity": "TFG", "capture_video": false, "env_id": "CartPole-v1", "total_timesteps": 500, "num_updates": 70, "buffer_size": 10000, "update_epochs": 10, "update_policy_epochs": 450, "num_rollouts": 8, "num_envs": 2, "gamma": 1, "policy_lr_start": 0.06548824413400488, "policy_lr_end": 0.0004704992874039154, "q_lr_start": 0.0517363360590694, "q_lr_end": 5.172503184677546e-05, "alpha": 0.6380395140274236, "eta": 1.379141379818223, "autotune": false, "target_entropy_scale": 0.1, "linear_schedule": false, "__trial_index__": 1}, "time_since_restore": 49.05845022201538, "iterations_since_restore": 19}
{"reward": 9.0, "timestamp": 1711475056, "checkpoint_dir_name": null, "done": false, "training_iteration": 20, "trial_id": "a29fb57c", "date": "2024-03-26_18-44-16", "time_this_iter_s": 2.886317014694214, "time_total_s": 51.944767236709595, "pid": 5327, "hostname": "Nicolass-Air.technicolor.net", "node_ip": "127.0.0.1", "config": {"exp_name": "QREPS", "seed": 1, "torch_deterministic": true, "cuda": true, "track": false, "wandb_project_name": "QREPS_CartPole-v1", "wandb_entity": "TFG", "capture_video": false, "env_id": "CartPole-v1", "total_timesteps": 500, "num_updates": 70, "buffer_size": 10000, "update_epochs": 10, "update_policy_epochs": 450, "num_rollouts": 8, "num_envs": 2, "gamma": 1, "policy_lr_start": 0.06548824413400488, "policy_lr_end": 0.0004704992874039154, "q_lr_start": 0.0517363360590694, "q_lr_end": 5.172503184677546e-05, "alpha": 0.6380395140274236, "eta": 1.379141379818223, "autotune": false, "target_entropy_scale": 0.1, "linear_schedule": false, "__trial_index__": 1}, "time_since_restore": 51.944767236709595, "iterations_since_restore": 20}
{"reward": 9.0, "timestamp": 1711475058, "checkpoint_dir_name": null, "done": false, "training_iteration": 21, "trial_id": "a29fb57c", "date": "2024-03-26_18-44-18", "time_this_iter_s": 2.382187604904175, "time_total_s": 54.32695484161377, "pid": 5327, "hostname": "Nicolass-Air.technicolor.net", "node_ip": "127.0.0.1", "config": {"exp_name": "QREPS", "seed": 1, "torch_deterministic": true, "cuda": true, "track": false, "wandb_project_name": "QREPS_CartPole-v1", "wandb_entity": "TFG", "capture_video": false, "env_id": "CartPole-v1", "total_timesteps": 500, "num_updates": 70, "buffer_size": 10000, "update_epochs": 10, "update_policy_epochs": 450, "num_rollouts": 8, "num_envs": 2, "gamma": 1, "policy_lr_start": 0.06548824413400488, "policy_lr_end": 0.0004704992874039154, "q_lr_start": 0.0517363360590694, "q_lr_end": 5.172503184677546e-05, "alpha": 0.6380395140274236, "eta": 1.379141379818223, "autotune": false, "target_entropy_scale": 0.1, "linear_schedule": false, "__trial_index__": 1}, "time_since_restore": 54.32695484161377, "iterations_since_restore": 21}
{"reward": 9.0, "timestamp": 1711475061, "checkpoint_dir_name": null, "done": false, "training_iteration": 22, "trial_id": "a29fb57c", "date": "2024-03-26_18-44-21", "time_this_iter_s": 2.718266010284424, "time_total_s": 57.04522085189819, "pid": 5327, "hostname": "Nicolass-Air.technicolor.net", "node_ip": "127.0.0.1", "config": {"exp_name": "QREPS", "seed": 1, "torch_deterministic": true, "cuda": true, "track": false, "wandb_project_name": "QREPS_CartPole-v1", "wandb_entity": "TFG", "capture_video": false, "env_id": "CartPole-v1", "total_timesteps": 500, "num_updates": 70, "buffer_size": 10000, "update_epochs": 10, "update_policy_epochs": 450, "num_rollouts": 8, "num_envs": 2, "gamma": 1, "policy_lr_start": 0.06548824413400488, "policy_lr_end": 0.0004704992874039154, "q_lr_start": 0.0517363360590694, "q_lr_end": 5.172503184677546e-05, "alpha": 0.6380395140274236, "eta": 1.379141379818223, "autotune": false, "target_entropy_scale": 0.1, "linear_schedule": false, "__trial_index__": 1}, "time_since_restore": 57.04522085189819, "iterations_since_restore": 22}
{"reward": 9.0, "timestamp": 1711475064, "checkpoint_dir_name": null, "done": false, "training_iteration": 23, "trial_id": "a29fb57c", "date": "2024-03-26_18-44-24", "time_this_iter_s": 2.5012428760528564, "time_total_s": 59.54646372795105, "pid": 5327, "hostname": "Nicolass-Air.technicolor.net", "node_ip": "127.0.0.1", "config": {"exp_name": "QREPS", "seed": 1, "torch_deterministic": true, "cuda": true, "track": false, "wandb_project_name": "QREPS_CartPole-v1", "wandb_entity": "TFG", "capture_video": false, "env_id": "CartPole-v1", "total_timesteps": 500, "num_updates": 70, "buffer_size": 10000, "update_epochs": 10, "update_policy_epochs": 450, "num_rollouts": 8, "num_envs": 2, "gamma": 1, "policy_lr_start": 0.06548824413400488, "policy_lr_end": 0.0004704992874039154, "q_lr_start": 0.0517363360590694, "q_lr_end": 5.172503184677546e-05, "alpha": 0.6380395140274236, "eta": 1.379141379818223, "autotune": false, "target_entropy_scale": 0.1, "linear_schedule": false, "__trial_index__": 1}, "time_since_restore": 59.54646372795105, "iterations_since_restore": 23}
{"reward": 9.0, "timestamp": 1711475066, "checkpoint_dir_name": null, "done": false, "training_iteration": 24, "trial_id": "a29fb57c", "date": "2024-03-26_18-44-26", "time_this_iter_s": 2.561760187149048, "time_total_s": 62.1082239151001, "pid": 5327, "hostname": "Nicolass-Air.technicolor.net", "node_ip": "127.0.0.1", "config": {"exp_name": "QREPS", "seed": 1, "torch_deterministic": true, "cuda": true, "track": false, "wandb_project_name": "QREPS_CartPole-v1", "wandb_entity": "TFG", "capture_video": false, "env_id": "CartPole-v1", "total_timesteps": 500, "num_updates": 70, "buffer_size": 10000, "update_epochs": 10, "update_policy_epochs": 450, "num_rollouts": 8, "num_envs": 2, "gamma": 1, "policy_lr_start": 0.06548824413400488, "policy_lr_end": 0.0004704992874039154, "q_lr_start": 0.0517363360590694, "q_lr_end": 5.172503184677546e-05, "alpha": 0.6380395140274236, "eta": 1.379141379818223, "autotune": false, "target_entropy_scale": 0.1, "linear_schedule": false, "__trial_index__": 1}, "time_since_restore": 62.1082239151001, "iterations_since_restore": 24}
{"reward": 9.0, "timestamp": 1711475069, "checkpoint_dir_name": null, "done": false, "training_iteration": 25, "trial_id": "a29fb57c", "date": "2024-03-26_18-44-29", "time_this_iter_s": 2.5172250270843506, "time_total_s": 64.62544894218445, "pid": 5327, "hostname": "Nicolass-Air.technicolor.net", "node_ip": "127.0.0.1", "config": {"exp_name": "QREPS", "seed": 1, "torch_deterministic": true, "cuda": true, "track": false, "wandb_project_name": "QREPS_CartPole-v1", "wandb_entity": "TFG", "capture_video": false, "env_id": "CartPole-v1", "total_timesteps": 500, "num_updates": 70, "buffer_size": 10000, "update_epochs": 10, "update_policy_epochs": 450, "num_rollouts": 8, "num_envs": 2, "gamma": 1, "policy_lr_start": 0.06548824413400488, "policy_lr_end": 0.0004704992874039154, "q_lr_start": 0.0517363360590694, "q_lr_end": 5.172503184677546e-05, "alpha": 0.6380395140274236, "eta": 1.379141379818223, "autotune": false, "target_entropy_scale": 0.1, "linear_schedule": false, "__trial_index__": 1}, "time_since_restore": 64.62544894218445, "iterations_since_restore": 25}
{"reward": 9.0, "timestamp": 1711475071, "checkpoint_dir_name": null, "done": false, "training_iteration": 26, "trial_id": "a29fb57c", "date": "2024-03-26_18-44-31", "time_this_iter_s": 2.2656848430633545, "time_total_s": 66.8911337852478, "pid": 5327, "hostname": "Nicolass-Air.technicolor.net", "node_ip": "127.0.0.1", "config": {"exp_name": "QREPS", "seed": 1, "torch_deterministic": true, "cuda": true, "track": false, "wandb_project_name": "QREPS_CartPole-v1", "wandb_entity": "TFG", "capture_video": false, "env_id": "CartPole-v1", "total_timesteps": 500, "num_updates": 70, "buffer_size": 10000, "update_epochs": 10, "update_policy_epochs": 450, "num_rollouts": 8, "num_envs": 2, "gamma": 1, "policy_lr_start": 0.06548824413400488, "policy_lr_end": 0.0004704992874039154, "q_lr_start": 0.0517363360590694, "q_lr_end": 5.172503184677546e-05, "alpha": 0.6380395140274236, "eta": 1.379141379818223, "autotune": false, "target_entropy_scale": 0.1, "linear_schedule": false, "__trial_index__": 1}, "time_since_restore": 66.8911337852478, "iterations_since_restore": 26}
{"reward": 9.0, "timestamp": 1711475074, "checkpoint_dir_name": null, "done": false, "training_iteration": 27, "trial_id": "a29fb57c", "date": "2024-03-26_18-44-34", "time_this_iter_s": 2.7901039123535156, "time_total_s": 69.68123769760132, "pid": 5327, "hostname": "Nicolass-Air.technicolor.net", "node_ip": "127.0.0.1", "config": {"exp_name": "QREPS", "seed": 1, "torch_deterministic": true, "cuda": true, "track": false, "wandb_project_name": "QREPS_CartPole-v1", "wandb_entity": "TFG", "capture_video": false, "env_id": "CartPole-v1", "total_timesteps": 500, "num_updates": 70, "buffer_size": 10000, "update_epochs": 10, "update_policy_epochs": 450, "num_rollouts": 8, "num_envs": 2, "gamma": 1, "policy_lr_start": 0.06548824413400488, "policy_lr_end": 0.0004704992874039154, "q_lr_start": 0.0517363360590694, "q_lr_end": 5.172503184677546e-05, "alpha": 0.6380395140274236, "eta": 1.379141379818223, "autotune": false, "target_entropy_scale": 0.1, "linear_schedule": false, "__trial_index__": 1}, "time_since_restore": 69.68123769760132, "iterations_since_restore": 27}
{"reward": 9.0, "timestamp": 1711475076, "checkpoint_dir_name": null, "done": false, "training_iteration": 28, "trial_id": "a29fb57c", "date": "2024-03-26_18-44-36", "time_this_iter_s": 2.5229198932647705, "time_total_s": 72.20415759086609, "pid": 5327, "hostname": "Nicolass-Air.technicolor.net", "node_ip": "127.0.0.1", "config": {"exp_name": "QREPS", "seed": 1, "torch_deterministic": true, "cuda": true, "track": false, "wandb_project_name": "QREPS_CartPole-v1", "wandb_entity": "TFG", "capture_video": false, "env_id": "CartPole-v1", "total_timesteps": 500, "num_updates": 70, "buffer_size": 10000, "update_epochs": 10, "update_policy_epochs": 450, "num_rollouts": 8, "num_envs": 2, "gamma": 1, "policy_lr_start": 0.06548824413400488, "policy_lr_end": 0.0004704992874039154, "q_lr_start": 0.0517363360590694, "q_lr_end": 5.172503184677546e-05, "alpha": 0.6380395140274236, "eta": 1.379141379818223, "autotune": false, "target_entropy_scale": 0.1, "linear_schedule": false, "__trial_index__": 1}, "time_since_restore": 72.20415759086609, "iterations_since_restore": 28}
{"reward": 9.0, "timestamp": 1711475078, "checkpoint_dir_name": null, "done": false, "training_iteration": 29, "trial_id": "a29fb57c", "date": "2024-03-26_18-44-38", "time_this_iter_s": 2.2738218307495117, "time_total_s": 74.4779794216156, "pid": 5327, "hostname": "Nicolass-Air.technicolor.net", "node_ip": "127.0.0.1", "config": {"exp_name": "QREPS", "seed": 1, "torch_deterministic": true, "cuda": true, "track": false, "wandb_project_name": "QREPS_CartPole-v1", "wandb_entity": "TFG", "capture_video": false, "env_id": "CartPole-v1", "total_timesteps": 500, "num_updates": 70, "buffer_size": 10000, "update_epochs": 10, "update_policy_epochs": 450, "num_rollouts": 8, "num_envs": 2, "gamma": 1, "policy_lr_start": 0.06548824413400488, "policy_lr_end": 0.0004704992874039154, "q_lr_start": 0.0517363360590694, "q_lr_end": 5.172503184677546e-05, "alpha": 0.6380395140274236, "eta": 1.379141379818223, "autotune": false, "target_entropy_scale": 0.1, "linear_schedule": false, "__trial_index__": 1}, "time_since_restore": 74.4779794216156, "iterations_since_restore": 29}
{"reward": 9.0, "timestamp": 1711475081, "checkpoint_dir_name": null, "done": false, "training_iteration": 30, "trial_id": "a29fb57c", "date": "2024-03-26_18-44-41", "time_this_iter_s": 2.094435930252075, "time_total_s": 76.57241535186768, "pid": 5327, "hostname": "Nicolass-Air.technicolor.net", "node_ip": "127.0.0.1", "config": {"exp_name": "QREPS", "seed": 1, "torch_deterministic": true, "cuda": true, "track": false, "wandb_project_name": "QREPS_CartPole-v1", "wandb_entity": "TFG", "capture_video": false, "env_id": "CartPole-v1", "total_timesteps": 500, "num_updates": 70, "buffer_size": 10000, "update_epochs": 10, "update_policy_epochs": 450, "num_rollouts": 8, "num_envs": 2, "gamma": 1, "policy_lr_start": 0.06548824413400488, "policy_lr_end": 0.0004704992874039154, "q_lr_start": 0.0517363360590694, "q_lr_end": 5.172503184677546e-05, "alpha": 0.6380395140274236, "eta": 1.379141379818223, "autotune": false, "target_entropy_scale": 0.1, "linear_schedule": false, "__trial_index__": 1}, "time_since_restore": 76.57241535186768, "iterations_since_restore": 30}
{"reward": 9.0, "timestamp": 1711475083, "checkpoint_dir_name": null, "done": false, "training_iteration": 31, "trial_id": "a29fb57c", "date": "2024-03-26_18-44-43", "time_this_iter_s": 2.063425064086914, "time_total_s": 78.63584041595459, "pid": 5327, "hostname": "Nicolass-Air.technicolor.net", "node_ip": "127.0.0.1", "config": {"exp_name": "QREPS", "seed": 1, "torch_deterministic": true, "cuda": true, "track": false, "wandb_project_name": "QREPS_CartPole-v1", "wandb_entity": "TFG", "capture_video": false, "env_id": "CartPole-v1", "total_timesteps": 500, "num_updates": 70, "buffer_size": 10000, "update_epochs": 10, "update_policy_epochs": 450, "num_rollouts": 8, "num_envs": 2, "gamma": 1, "policy_lr_start": 0.06548824413400488, "policy_lr_end": 0.0004704992874039154, "q_lr_start": 0.0517363360590694, "q_lr_end": 5.172503184677546e-05, "alpha": 0.6380395140274236, "eta": 1.379141379818223, "autotune": false, "target_entropy_scale": 0.1, "linear_schedule": false, "__trial_index__": 1}, "time_since_restore": 78.63584041595459, "iterations_since_restore": 31}
{"reward": 9.0, "timestamp": 1711475085, "checkpoint_dir_name": null, "done": false, "training_iteration": 32, "trial_id": "a29fb57c", "date": "2024-03-26_18-44-45", "time_this_iter_s": 2.186331033706665, "time_total_s": 80.82217144966125, "pid": 5327, "hostname": "Nicolass-Air.technicolor.net", "node_ip": "127.0.0.1", "config": {"exp_name": "QREPS", "seed": 1, "torch_deterministic": true, "cuda": true, "track": false, "wandb_project_name": "QREPS_CartPole-v1", "wandb_entity": "TFG", "capture_video": false, "env_id": "CartPole-v1", "total_timesteps": 500, "num_updates": 70, "buffer_size": 10000, "update_epochs": 10, "update_policy_epochs": 450, "num_rollouts": 8, "num_envs": 2, "gamma": 1, "policy_lr_start": 0.06548824413400488, "policy_lr_end": 0.0004704992874039154, "q_lr_start": 0.0517363360590694, "q_lr_end": 5.172503184677546e-05, "alpha": 0.6380395140274236, "eta": 1.379141379818223, "autotune": false, "target_entropy_scale": 0.1, "linear_schedule": false, "__trial_index__": 1}, "time_since_restore": 80.82217144966125, "iterations_since_restore": 32}
{"reward": 9.0, "timestamp": 1711475087, "checkpoint_dir_name": null, "done": false, "training_iteration": 33, "trial_id": "a29fb57c", "date": "2024-03-26_18-44-47", "time_this_iter_s": 1.9765770435333252, "time_total_s": 82.79874849319458, "pid": 5327, "hostname": "Nicolass-Air.technicolor.net", "node_ip": "127.0.0.1", "config": {"exp_name": "QREPS", "seed": 1, "torch_deterministic": true, "cuda": true, "track": false, "wandb_project_name": "QREPS_CartPole-v1", "wandb_entity": "TFG", "capture_video": false, "env_id": "CartPole-v1", "total_timesteps": 500, "num_updates": 70, "buffer_size": 10000, "update_epochs": 10, "update_policy_epochs": 450, "num_rollouts": 8, "num_envs": 2, "gamma": 1, "policy_lr_start": 0.06548824413400488, "policy_lr_end": 0.0004704992874039154, "q_lr_start": 0.0517363360590694, "q_lr_end": 5.172503184677546e-05, "alpha": 0.6380395140274236, "eta": 1.379141379818223, "autotune": false, "target_entropy_scale": 0.1, "linear_schedule": false, "__trial_index__": 1}, "time_since_restore": 82.79874849319458, "iterations_since_restore": 33}
{"reward": 9.0, "timestamp": 1711475089, "checkpoint_dir_name": null, "done": false, "training_iteration": 34, "trial_id": "a29fb57c", "date": "2024-03-26_18-44-49", "time_this_iter_s": 1.972046136856079, "time_total_s": 84.77079463005066, "pid": 5327, "hostname": "Nicolass-Air.technicolor.net", "node_ip": "127.0.0.1", "config": {"exp_name": "QREPS", "seed": 1, "torch_deterministic": true, "cuda": true, "track": false, "wandb_project_name": "QREPS_CartPole-v1", "wandb_entity": "TFG", "capture_video": false, "env_id": "CartPole-v1", "total_timesteps": 500, "num_updates": 70, "buffer_size": 10000, "update_epochs": 10, "update_policy_epochs": 450, "num_rollouts": 8, "num_envs": 2, "gamma": 1, "policy_lr_start": 0.06548824413400488, "policy_lr_end": 0.0004704992874039154, "q_lr_start": 0.0517363360590694, "q_lr_end": 5.172503184677546e-05, "alpha": 0.6380395140274236, "eta": 1.379141379818223, "autotune": false, "target_entropy_scale": 0.1, "linear_schedule": false, "__trial_index__": 1}, "time_since_restore": 84.77079463005066, "iterations_since_restore": 34}
{"reward": 9.0, "timestamp": 1711475091, "checkpoint_dir_name": null, "done": false, "training_iteration": 35, "trial_id": "a29fb57c", "date": "2024-03-26_18-44-51", "time_this_iter_s": 2.145155906677246, "time_total_s": 86.9159505367279, "pid": 5327, "hostname": "Nicolass-Air.technicolor.net", "node_ip": "127.0.0.1", "config": {"exp_name": "QREPS", "seed": 1, "torch_deterministic": true, "cuda": true, "track": false, "wandb_project_name": "QREPS_CartPole-v1", "wandb_entity": "TFG", "capture_video": false, "env_id": "CartPole-v1", "total_timesteps": 500, "num_updates": 70, "buffer_size": 10000, "update_epochs": 10, "update_policy_epochs": 450, "num_rollouts": 8, "num_envs": 2, "gamma": 1, "policy_lr_start": 0.06548824413400488, "policy_lr_end": 0.0004704992874039154, "q_lr_start": 0.0517363360590694, "q_lr_end": 5.172503184677546e-05, "alpha": 0.6380395140274236, "eta": 1.379141379818223, "autotune": false, "target_entropy_scale": 0.1, "linear_schedule": false, "__trial_index__": 1}, "time_since_restore": 86.9159505367279, "iterations_since_restore": 35}
{"reward": 9.0, "timestamp": 1711475093, "checkpoint_dir_name": null, "done": false, "training_iteration": 36, "trial_id": "a29fb57c", "date": "2024-03-26_18-44-53", "time_this_iter_s": 1.8890550136566162, "time_total_s": 88.80500555038452, "pid": 5327, "hostname": "Nicolass-Air.technicolor.net", "node_ip": "127.0.0.1", "config": {"exp_name": "QREPS", "seed": 1, "torch_deterministic": true, "cuda": true, "track": false, "wandb_project_name": "QREPS_CartPole-v1", "wandb_entity": "TFG", "capture_video": false, "env_id": "CartPole-v1", "total_timesteps": 500, "num_updates": 70, "buffer_size": 10000, "update_epochs": 10, "update_policy_epochs": 450, "num_rollouts": 8, "num_envs": 2, "gamma": 1, "policy_lr_start": 0.06548824413400488, "policy_lr_end": 0.0004704992874039154, "q_lr_start": 0.0517363360590694, "q_lr_end": 5.172503184677546e-05, "alpha": 0.6380395140274236, "eta": 1.379141379818223, "autotune": false, "target_entropy_scale": 0.1, "linear_schedule": false, "__trial_index__": 1}, "time_since_restore": 88.80500555038452, "iterations_since_restore": 36}
{"reward": 9.0, "timestamp": 1711475095, "checkpoint_dir_name": null, "done": false, "training_iteration": 37, "trial_id": "a29fb57c", "date": "2024-03-26_18-44-55", "time_this_iter_s": 1.945476770401001, "time_total_s": 90.75048232078552, "pid": 5327, "hostname": "Nicolass-Air.technicolor.net", "node_ip": "127.0.0.1", "config": {"exp_name": "QREPS", "seed": 1, "torch_deterministic": true, "cuda": true, "track": false, "wandb_project_name": "QREPS_CartPole-v1", "wandb_entity": "TFG", "capture_video": false, "env_id": "CartPole-v1", "total_timesteps": 500, "num_updates": 70, "buffer_size": 10000, "update_epochs": 10, "update_policy_epochs": 450, "num_rollouts": 8, "num_envs": 2, "gamma": 1, "policy_lr_start": 0.06548824413400488, "policy_lr_end": 0.0004704992874039154, "q_lr_start": 0.0517363360590694, "q_lr_end": 5.172503184677546e-05, "alpha": 0.6380395140274236, "eta": 1.379141379818223, "autotune": false, "target_entropy_scale": 0.1, "linear_schedule": false, "__trial_index__": 1}, "time_since_restore": 90.75048232078552, "iterations_since_restore": 37}
{"reward": 9.0, "timestamp": 1711475097, "checkpoint_dir_name": null, "done": false, "training_iteration": 38, "trial_id": "a29fb57c", "date": "2024-03-26_18-44-57", "time_this_iter_s": 1.9672048091888428, "time_total_s": 92.71768712997437, "pid": 5327, "hostname": "Nicolass-Air.technicolor.net", "node_ip": "127.0.0.1", "config": {"exp_name": "QREPS", "seed": 1, "torch_deterministic": true, "cuda": true, "track": false, "wandb_project_name": "QREPS_CartPole-v1", "wandb_entity": "TFG", "capture_video": false, "env_id": "CartPole-v1", "total_timesteps": 500, "num_updates": 70, "buffer_size": 10000, "update_epochs": 10, "update_policy_epochs": 450, "num_rollouts": 8, "num_envs": 2, "gamma": 1, "policy_lr_start": 0.06548824413400488, "policy_lr_end": 0.0004704992874039154, "q_lr_start": 0.0517363360590694, "q_lr_end": 5.172503184677546e-05, "alpha": 0.6380395140274236, "eta": 1.379141379818223, "autotune": false, "target_entropy_scale": 0.1, "linear_schedule": false, "__trial_index__": 1}, "time_since_restore": 92.71768712997437, "iterations_since_restore": 38}
{"reward": 9.0, "timestamp": 1711475099, "checkpoint_dir_name": null, "done": false, "training_iteration": 39, "trial_id": "a29fb57c", "date": "2024-03-26_18-44-59", "time_this_iter_s": 2.032658100128174, "time_total_s": 94.75034523010254, "pid": 5327, "hostname": "Nicolass-Air.technicolor.net", "node_ip": "127.0.0.1", "config": {"exp_name": "QREPS", "seed": 1, "torch_deterministic": true, "cuda": true, "track": false, "wandb_project_name": "QREPS_CartPole-v1", "wandb_entity": "TFG", "capture_video": false, "env_id": "CartPole-v1", "total_timesteps": 500, "num_updates": 70, "buffer_size": 10000, "update_epochs": 10, "update_policy_epochs": 450, "num_rollouts": 8, "num_envs": 2, "gamma": 1, "policy_lr_start": 0.06548824413400488, "policy_lr_end": 0.0004704992874039154, "q_lr_start": 0.0517363360590694, "q_lr_end": 5.172503184677546e-05, "alpha": 0.6380395140274236, "eta": 1.379141379818223, "autotune": false, "target_entropy_scale": 0.1, "linear_schedule": false, "__trial_index__": 1}, "time_since_restore": 94.75034523010254, "iterations_since_restore": 39}
{"reward": 9.0, "timestamp": 1711475101, "checkpoint_dir_name": null, "done": false, "training_iteration": 40, "trial_id": "a29fb57c", "date": "2024-03-26_18-45-01", "time_this_iter_s": 2.262700080871582, "time_total_s": 97.01304531097412, "pid": 5327, "hostname": "Nicolass-Air.technicolor.net", "node_ip": "127.0.0.1", "config": {"exp_name": "QREPS", "seed": 1, "torch_deterministic": true, "cuda": true, "track": false, "wandb_project_name": "QREPS_CartPole-v1", "wandb_entity": "TFG", "capture_video": false, "env_id": "CartPole-v1", "total_timesteps": 500, "num_updates": 70, "buffer_size": 10000, "update_epochs": 10, "update_policy_epochs": 450, "num_rollouts": 8, "num_envs": 2, "gamma": 1, "policy_lr_start": 0.06548824413400488, "policy_lr_end": 0.0004704992874039154, "q_lr_start": 0.0517363360590694, "q_lr_end": 5.172503184677546e-05, "alpha": 0.6380395140274236, "eta": 1.379141379818223, "autotune": false, "target_entropy_scale": 0.1, "linear_schedule": false, "__trial_index__": 1}, "time_since_restore": 97.01304531097412, "iterations_since_restore": 40}
{"reward": 9.0, "timestamp": 1711475103, "checkpoint_dir_name": null, "done": false, "training_iteration": 41, "trial_id": "a29fb57c", "date": "2024-03-26_18-45-03", "time_this_iter_s": 1.9682981967926025, "time_total_s": 98.98134350776672, "pid": 5327, "hostname": "Nicolass-Air.technicolor.net", "node_ip": "127.0.0.1", "config": {"exp_name": "QREPS", "seed": 1, "torch_deterministic": true, "cuda": true, "track": false, "wandb_project_name": "QREPS_CartPole-v1", "wandb_entity": "TFG", "capture_video": false, "env_id": "CartPole-v1", "total_timesteps": 500, "num_updates": 70, "buffer_size": 10000, "update_epochs": 10, "update_policy_epochs": 450, "num_rollouts": 8, "num_envs": 2, "gamma": 1, "policy_lr_start": 0.06548824413400488, "policy_lr_end": 0.0004704992874039154, "q_lr_start": 0.0517363360590694, "q_lr_end": 5.172503184677546e-05, "alpha": 0.6380395140274236, "eta": 1.379141379818223, "autotune": false, "target_entropy_scale": 0.1, "linear_schedule": false, "__trial_index__": 1}, "time_since_restore": 98.98134350776672, "iterations_since_restore": 41}
{"reward": 9.0, "timestamp": 1711475105, "checkpoint_dir_name": null, "done": false, "training_iteration": 42, "trial_id": "a29fb57c", "date": "2024-03-26_18-45-05", "time_this_iter_s": 1.824526071548462, "time_total_s": 100.80586957931519, "pid": 5327, "hostname": "Nicolass-Air.technicolor.net", "node_ip": "127.0.0.1", "config": {"exp_name": "QREPS", "seed": 1, "torch_deterministic": true, "cuda": true, "track": false, "wandb_project_name": "QREPS_CartPole-v1", "wandb_entity": "TFG", "capture_video": false, "env_id": "CartPole-v1", "total_timesteps": 500, "num_updates": 70, "buffer_size": 10000, "update_epochs": 10, "update_policy_epochs": 450, "num_rollouts": 8, "num_envs": 2, "gamma": 1, "policy_lr_start": 0.06548824413400488, "policy_lr_end": 0.0004704992874039154, "q_lr_start": 0.0517363360590694, "q_lr_end": 5.172503184677546e-05, "alpha": 0.6380395140274236, "eta": 1.379141379818223, "autotune": false, "target_entropy_scale": 0.1, "linear_schedule": false, "__trial_index__": 1}, "time_since_restore": 100.80586957931519, "iterations_since_restore": 42}
{"reward": 9.0, "timestamp": 1711475107, "checkpoint_dir_name": null, "done": false, "training_iteration": 43, "trial_id": "a29fb57c", "date": "2024-03-26_18-45-07", "time_this_iter_s": 2.243481159210205, "time_total_s": 103.04935073852539, "pid": 5327, "hostname": "Nicolass-Air.technicolor.net", "node_ip": "127.0.0.1", "config": {"exp_name": "QREPS", "seed": 1, "torch_deterministic": true, "cuda": true, "track": false, "wandb_project_name": "QREPS_CartPole-v1", "wandb_entity": "TFG", "capture_video": false, "env_id": "CartPole-v1", "total_timesteps": 500, "num_updates": 70, "buffer_size": 10000, "update_epochs": 10, "update_policy_epochs": 450, "num_rollouts": 8, "num_envs": 2, "gamma": 1, "policy_lr_start": 0.06548824413400488, "policy_lr_end": 0.0004704992874039154, "q_lr_start": 0.0517363360590694, "q_lr_end": 5.172503184677546e-05, "alpha": 0.6380395140274236, "eta": 1.379141379818223, "autotune": false, "target_entropy_scale": 0.1, "linear_schedule": false, "__trial_index__": 1}, "time_since_restore": 103.04935073852539, "iterations_since_restore": 43}
{"reward": 9.0, "timestamp": 1711475110, "checkpoint_dir_name": null, "done": false, "training_iteration": 44, "trial_id": "a29fb57c", "date": "2024-03-26_18-45-10", "time_this_iter_s": 2.4781129360198975, "time_total_s": 105.52746367454529, "pid": 5327, "hostname": "Nicolass-Air.technicolor.net", "node_ip": "127.0.0.1", "config": {"exp_name": "QREPS", "seed": 1, "torch_deterministic": true, "cuda": true, "track": false, "wandb_project_name": "QREPS_CartPole-v1", "wandb_entity": "TFG", "capture_video": false, "env_id": "CartPole-v1", "total_timesteps": 500, "num_updates": 70, "buffer_size": 10000, "update_epochs": 10, "update_policy_epochs": 450, "num_rollouts": 8, "num_envs": 2, "gamma": 1, "policy_lr_start": 0.06548824413400488, "policy_lr_end": 0.0004704992874039154, "q_lr_start": 0.0517363360590694, "q_lr_end": 5.172503184677546e-05, "alpha": 0.6380395140274236, "eta": 1.379141379818223, "autotune": false, "target_entropy_scale": 0.1, "linear_schedule": false, "__trial_index__": 1}, "time_since_restore": 105.52746367454529, "iterations_since_restore": 44}
{"reward": 9.0, "timestamp": 1711475112, "checkpoint_dir_name": null, "done": false, "training_iteration": 45, "trial_id": "a29fb57c", "date": "2024-03-26_18-45-12", "time_this_iter_s": 2.690802812576294, "time_total_s": 108.21826648712158, "pid": 5327, "hostname": "Nicolass-Air.technicolor.net", "node_ip": "127.0.0.1", "config": {"exp_name": "QREPS", "seed": 1, "torch_deterministic": true, "cuda": true, "track": false, "wandb_project_name": "QREPS_CartPole-v1", "wandb_entity": "TFG", "capture_video": false, "env_id": "CartPole-v1", "total_timesteps": 500, "num_updates": 70, "buffer_size": 10000, "update_epochs": 10, "update_policy_epochs": 450, "num_rollouts": 8, "num_envs": 2, "gamma": 1, "policy_lr_start": 0.06548824413400488, "policy_lr_end": 0.0004704992874039154, "q_lr_start": 0.0517363360590694, "q_lr_end": 5.172503184677546e-05, "alpha": 0.6380395140274236, "eta": 1.379141379818223, "autotune": false, "target_entropy_scale": 0.1, "linear_schedule": false, "__trial_index__": 1}, "time_since_restore": 108.21826648712158, "iterations_since_restore": 45}
{"reward": 9.0, "timestamp": 1711475115, "checkpoint_dir_name": null, "done": false, "training_iteration": 46, "trial_id": "a29fb57c", "date": "2024-03-26_18-45-15", "time_this_iter_s": 2.396300792694092, "time_total_s": 110.61456727981567, "pid": 5327, "hostname": "Nicolass-Air.technicolor.net", "node_ip": "127.0.0.1", "config": {"exp_name": "QREPS", "seed": 1, "torch_deterministic": true, "cuda": true, "track": false, "wandb_project_name": "QREPS_CartPole-v1", "wandb_entity": "TFG", "capture_video": false, "env_id": "CartPole-v1", "total_timesteps": 500, "num_updates": 70, "buffer_size": 10000, "update_epochs": 10, "update_policy_epochs": 450, "num_rollouts": 8, "num_envs": 2, "gamma": 1, "policy_lr_start": 0.06548824413400488, "policy_lr_end": 0.0004704992874039154, "q_lr_start": 0.0517363360590694, "q_lr_end": 5.172503184677546e-05, "alpha": 0.6380395140274236, "eta": 1.379141379818223, "autotune": false, "target_entropy_scale": 0.1, "linear_schedule": false, "__trial_index__": 1}, "time_since_restore": 110.61456727981567, "iterations_since_restore": 46}
{"reward": 9.0, "timestamp": 1711475117, "checkpoint_dir_name": null, "done": false, "training_iteration": 47, "trial_id": "a29fb57c", "date": "2024-03-26_18-45-17", "time_this_iter_s": 2.455735921859741, "time_total_s": 113.07030320167542, "pid": 5327, "hostname": "Nicolass-Air.technicolor.net", "node_ip": "127.0.0.1", "config": {"exp_name": "QREPS", "seed": 1, "torch_deterministic": true, "cuda": true, "track": false, "wandb_project_name": "QREPS_CartPole-v1", "wandb_entity": "TFG", "capture_video": false, "env_id": "CartPole-v1", "total_timesteps": 500, "num_updates": 70, "buffer_size": 10000, "update_epochs": 10, "update_policy_epochs": 450, "num_rollouts": 8, "num_envs": 2, "gamma": 1, "policy_lr_start": 0.06548824413400488, "policy_lr_end": 0.0004704992874039154, "q_lr_start": 0.0517363360590694, "q_lr_end": 5.172503184677546e-05, "alpha": 0.6380395140274236, "eta": 1.379141379818223, "autotune": false, "target_entropy_scale": 0.1, "linear_schedule": false, "__trial_index__": 1}, "time_since_restore": 113.07030320167542, "iterations_since_restore": 47}
{"reward": 9.0, "timestamp": 1711475120, "checkpoint_dir_name": null, "done": false, "training_iteration": 48, "trial_id": "a29fb57c", "date": "2024-03-26_18-45-20", "time_this_iter_s": 3.0867419242858887, "time_total_s": 116.1570451259613, "pid": 5327, "hostname": "Nicolass-Air.technicolor.net", "node_ip": "127.0.0.1", "config": {"exp_name": "QREPS", "seed": 1, "torch_deterministic": true, "cuda": true, "track": false, "wandb_project_name": "QREPS_CartPole-v1", "wandb_entity": "TFG", "capture_video": false, "env_id": "CartPole-v1", "total_timesteps": 500, "num_updates": 70, "buffer_size": 10000, "update_epochs": 10, "update_policy_epochs": 450, "num_rollouts": 8, "num_envs": 2, "gamma": 1, "policy_lr_start": 0.06548824413400488, "policy_lr_end": 0.0004704992874039154, "q_lr_start": 0.0517363360590694, "q_lr_end": 5.172503184677546e-05, "alpha": 0.6380395140274236, "eta": 1.379141379818223, "autotune": false, "target_entropy_scale": 0.1, "linear_schedule": false, "__trial_index__": 1}, "time_since_restore": 116.1570451259613, "iterations_since_restore": 48}
{"reward": 9.0, "timestamp": 1711475123, "checkpoint_dir_name": null, "done": false, "training_iteration": 49, "trial_id": "a29fb57c", "date": "2024-03-26_18-45-23", "time_this_iter_s": 2.46085786819458, "time_total_s": 118.61790299415588, "pid": 5327, "hostname": "Nicolass-Air.technicolor.net", "node_ip": "127.0.0.1", "config": {"exp_name": "QREPS", "seed": 1, "torch_deterministic": true, "cuda": true, "track": false, "wandb_project_name": "QREPS_CartPole-v1", "wandb_entity": "TFG", "capture_video": false, "env_id": "CartPole-v1", "total_timesteps": 500, "num_updates": 70, "buffer_size": 10000, "update_epochs": 10, "update_policy_epochs": 450, "num_rollouts": 8, "num_envs": 2, "gamma": 1, "policy_lr_start": 0.06548824413400488, "policy_lr_end": 0.0004704992874039154, "q_lr_start": 0.0517363360590694, "q_lr_end": 5.172503184677546e-05, "alpha": 0.6380395140274236, "eta": 1.379141379818223, "autotune": false, "target_entropy_scale": 0.1, "linear_schedule": false, "__trial_index__": 1}, "time_since_restore": 118.61790299415588, "iterations_since_restore": 49}
{"reward": 9.0, "timestamp": 1711475125, "checkpoint_dir_name": null, "done": false, "training_iteration": 50, "trial_id": "a29fb57c", "date": "2024-03-26_18-45-25", "time_this_iter_s": 2.412410259246826, "time_total_s": 121.03031325340271, "pid": 5327, "hostname": "Nicolass-Air.technicolor.net", "node_ip": "127.0.0.1", "config": {"exp_name": "QREPS", "seed": 1, "torch_deterministic": true, "cuda": true, "track": false, "wandb_project_name": "QREPS_CartPole-v1", "wandb_entity": "TFG", "capture_video": false, "env_id": "CartPole-v1", "total_timesteps": 500, "num_updates": 70, "buffer_size": 10000, "update_epochs": 10, "update_policy_epochs": 450, "num_rollouts": 8, "num_envs": 2, "gamma": 1, "policy_lr_start": 0.06548824413400488, "policy_lr_end": 0.0004704992874039154, "q_lr_start": 0.0517363360590694, "q_lr_end": 5.172503184677546e-05, "alpha": 0.6380395140274236, "eta": 1.379141379818223, "autotune": false, "target_entropy_scale": 0.1, "linear_schedule": false, "__trial_index__": 1}, "time_since_restore": 121.03031325340271, "iterations_since_restore": 50}
{"reward": 9.0, "timestamp": 1711475128, "checkpoint_dir_name": null, "done": false, "training_iteration": 51, "trial_id": "a29fb57c", "date": "2024-03-26_18-45-28", "time_this_iter_s": 2.8706531524658203, "time_total_s": 123.90096640586853, "pid": 5327, "hostname": "Nicolass-Air.technicolor.net", "node_ip": "127.0.0.1", "config": {"exp_name": "QREPS", "seed": 1, "torch_deterministic": true, "cuda": true, "track": false, "wandb_project_name": "QREPS_CartPole-v1", "wandb_entity": "TFG", "capture_video": false, "env_id": "CartPole-v1", "total_timesteps": 500, "num_updates": 70, "buffer_size": 10000, "update_epochs": 10, "update_policy_epochs": 450, "num_rollouts": 8, "num_envs": 2, "gamma": 1, "policy_lr_start": 0.06548824413400488, "policy_lr_end": 0.0004704992874039154, "q_lr_start": 0.0517363360590694, "q_lr_end": 5.172503184677546e-05, "alpha": 0.6380395140274236, "eta": 1.379141379818223, "autotune": false, "target_entropy_scale": 0.1, "linear_schedule": false, "__trial_index__": 1}, "time_since_restore": 123.90096640586853, "iterations_since_restore": 51}
{"reward": 9.0, "timestamp": 1711475130, "checkpoint_dir_name": null, "done": false, "training_iteration": 52, "trial_id": "a29fb57c", "date": "2024-03-26_18-45-30", "time_this_iter_s": 2.434619903564453, "time_total_s": 126.33558630943298, "pid": 5327, "hostname": "Nicolass-Air.technicolor.net", "node_ip": "127.0.0.1", "config": {"exp_name": "QREPS", "seed": 1, "torch_deterministic": true, "cuda": true, "track": false, "wandb_project_name": "QREPS_CartPole-v1", "wandb_entity": "TFG", "capture_video": false, "env_id": "CartPole-v1", "total_timesteps": 500, "num_updates": 70, "buffer_size": 10000, "update_epochs": 10, "update_policy_epochs": 450, "num_rollouts": 8, "num_envs": 2, "gamma": 1, "policy_lr_start": 0.06548824413400488, "policy_lr_end": 0.0004704992874039154, "q_lr_start": 0.0517363360590694, "q_lr_end": 5.172503184677546e-05, "alpha": 0.6380395140274236, "eta": 1.379141379818223, "autotune": false, "target_entropy_scale": 0.1, "linear_schedule": false, "__trial_index__": 1}, "time_since_restore": 126.33558630943298, "iterations_since_restore": 52}
{"reward": 9.0, "timestamp": 1711475133, "checkpoint_dir_name": null, "done": false, "training_iteration": 53, "trial_id": "a29fb57c", "date": "2024-03-26_18-45-33", "time_this_iter_s": 2.70839786529541, "time_total_s": 129.0439841747284, "pid": 5327, "hostname": "Nicolass-Air.technicolor.net", "node_ip": "127.0.0.1", "config": {"exp_name": "QREPS", "seed": 1, "torch_deterministic": true, "cuda": true, "track": false, "wandb_project_name": "QREPS_CartPole-v1", "wandb_entity": "TFG", "capture_video": false, "env_id": "CartPole-v1", "total_timesteps": 500, "num_updates": 70, "buffer_size": 10000, "update_epochs": 10, "update_policy_epochs": 450, "num_rollouts": 8, "num_envs": 2, "gamma": 1, "policy_lr_start": 0.06548824413400488, "policy_lr_end": 0.0004704992874039154, "q_lr_start": 0.0517363360590694, "q_lr_end": 5.172503184677546e-05, "alpha": 0.6380395140274236, "eta": 1.379141379818223, "autotune": false, "target_entropy_scale": 0.1, "linear_schedule": false, "__trial_index__": 1}, "time_since_restore": 129.0439841747284, "iterations_since_restore": 53}
{"reward": 9.0, "timestamp": 1711475136, "checkpoint_dir_name": null, "done": false, "training_iteration": 54, "trial_id": "a29fb57c", "date": "2024-03-26_18-45-36", "time_this_iter_s": 2.618640899658203, "time_total_s": 131.6626250743866, "pid": 5327, "hostname": "Nicolass-Air.technicolor.net", "node_ip": "127.0.0.1", "config": {"exp_name": "QREPS", "seed": 1, "torch_deterministic": true, "cuda": true, "track": false, "wandb_project_name": "QREPS_CartPole-v1", "wandb_entity": "TFG", "capture_video": false, "env_id": "CartPole-v1", "total_timesteps": 500, "num_updates": 70, "buffer_size": 10000, "update_epochs": 10, "update_policy_epochs": 450, "num_rollouts": 8, "num_envs": 2, "gamma": 1, "policy_lr_start": 0.06548824413400488, "policy_lr_end": 0.0004704992874039154, "q_lr_start": 0.0517363360590694, "q_lr_end": 5.172503184677546e-05, "alpha": 0.6380395140274236, "eta": 1.379141379818223, "autotune": false, "target_entropy_scale": 0.1, "linear_schedule": false, "__trial_index__": 1}, "time_since_restore": 131.6626250743866, "iterations_since_restore": 54}
{"reward": 9.0, "timestamp": 1711475138, "checkpoint_dir_name": null, "done": false, "training_iteration": 55, "trial_id": "a29fb57c", "date": "2024-03-26_18-45-38", "time_this_iter_s": 2.508563995361328, "time_total_s": 134.17118906974792, "pid": 5327, "hostname": "Nicolass-Air.technicolor.net", "node_ip": "127.0.0.1", "config": {"exp_name": "QREPS", "seed": 1, "torch_deterministic": true, "cuda": true, "track": false, "wandb_project_name": "QREPS_CartPole-v1", "wandb_entity": "TFG", "capture_video": false, "env_id": "CartPole-v1", "total_timesteps": 500, "num_updates": 70, "buffer_size": 10000, "update_epochs": 10, "update_policy_epochs": 450, "num_rollouts": 8, "num_envs": 2, "gamma": 1, "policy_lr_start": 0.06548824413400488, "policy_lr_end": 0.0004704992874039154, "q_lr_start": 0.0517363360590694, "q_lr_end": 5.172503184677546e-05, "alpha": 0.6380395140274236, "eta": 1.379141379818223, "autotune": false, "target_entropy_scale": 0.1, "linear_schedule": false, "__trial_index__": 1}, "time_since_restore": 134.17118906974792, "iterations_since_restore": 55}
{"reward": 9.0, "timestamp": 1711475141, "checkpoint_dir_name": null, "done": false, "training_iteration": 56, "trial_id": "a29fb57c", "date": "2024-03-26_18-45-41", "time_this_iter_s": 2.2809174060821533, "time_total_s": 136.45210647583008, "pid": 5327, "hostname": "Nicolass-Air.technicolor.net", "node_ip": "127.0.0.1", "config": {"exp_name": "QREPS", "seed": 1, "torch_deterministic": true, "cuda": true, "track": false, "wandb_project_name": "QREPS_CartPole-v1", "wandb_entity": "TFG", "capture_video": false, "env_id": "CartPole-v1", "total_timesteps": 500, "num_updates": 70, "buffer_size": 10000, "update_epochs": 10, "update_policy_epochs": 450, "num_rollouts": 8, "num_envs": 2, "gamma": 1, "policy_lr_start": 0.06548824413400488, "policy_lr_end": 0.0004704992874039154, "q_lr_start": 0.0517363360590694, "q_lr_end": 5.172503184677546e-05, "alpha": 0.6380395140274236, "eta": 1.379141379818223, "autotune": false, "target_entropy_scale": 0.1, "linear_schedule": false, "__trial_index__": 1}, "time_since_restore": 136.45210647583008, "iterations_since_restore": 56}
{"reward": 9.0, "timestamp": 1711475143, "checkpoint_dir_name": null, "done": false, "training_iteration": 57, "trial_id": "a29fb57c", "date": "2024-03-26_18-45-43", "time_this_iter_s": 2.076272964477539, "time_total_s": 138.52837944030762, "pid": 5327, "hostname": "Nicolass-Air.technicolor.net", "node_ip": "127.0.0.1", "config": {"exp_name": "QREPS", "seed": 1, "torch_deterministic": true, "cuda": true, "track": false, "wandb_project_name": "QREPS_CartPole-v1", "wandb_entity": "TFG", "capture_video": false, "env_id": "CartPole-v1", "total_timesteps": 500, "num_updates": 70, "buffer_size": 10000, "update_epochs": 10, "update_policy_epochs": 450, "num_rollouts": 8, "num_envs": 2, "gamma": 1, "policy_lr_start": 0.06548824413400488, "policy_lr_end": 0.0004704992874039154, "q_lr_start": 0.0517363360590694, "q_lr_end": 5.172503184677546e-05, "alpha": 0.6380395140274236, "eta": 1.379141379818223, "autotune": false, "target_entropy_scale": 0.1, "linear_schedule": false, "__trial_index__": 1}, "time_since_restore": 138.52837944030762, "iterations_since_restore": 57}
{"reward": 9.0, "timestamp": 1711475145, "checkpoint_dir_name": null, "done": false, "training_iteration": 58, "trial_id": "a29fb57c", "date": "2024-03-26_18-45-45", "time_this_iter_s": 2.056295871734619, "time_total_s": 140.58467531204224, "pid": 5327, "hostname": "Nicolass-Air.technicolor.net", "node_ip": "127.0.0.1", "config": {"exp_name": "QREPS", "seed": 1, "torch_deterministic": true, "cuda": true, "track": false, "wandb_project_name": "QREPS_CartPole-v1", "wandb_entity": "TFG", "capture_video": false, "env_id": "CartPole-v1", "total_timesteps": 500, "num_updates": 70, "buffer_size": 10000, "update_epochs": 10, "update_policy_epochs": 450, "num_rollouts": 8, "num_envs": 2, "gamma": 1, "policy_lr_start": 0.06548824413400488, "policy_lr_end": 0.0004704992874039154, "q_lr_start": 0.0517363360590694, "q_lr_end": 5.172503184677546e-05, "alpha": 0.6380395140274236, "eta": 1.379141379818223, "autotune": false, "target_entropy_scale": 0.1, "linear_schedule": false, "__trial_index__": 1}, "time_since_restore": 140.58467531204224, "iterations_since_restore": 58}
{"reward": 9.0, "timestamp": 1711475147, "checkpoint_dir_name": null, "done": false, "training_iteration": 59, "trial_id": "a29fb57c", "date": "2024-03-26_18-45-47", "time_this_iter_s": 2.0357120037078857, "time_total_s": 142.62038731575012, "pid": 5327, "hostname": "Nicolass-Air.technicolor.net", "node_ip": "127.0.0.1", "config": {"exp_name": "QREPS", "seed": 1, "torch_deterministic": true, "cuda": true, "track": false, "wandb_project_name": "QREPS_CartPole-v1", "wandb_entity": "TFG", "capture_video": false, "env_id": "CartPole-v1", "total_timesteps": 500, "num_updates": 70, "buffer_size": 10000, "update_epochs": 10, "update_policy_epochs": 450, "num_rollouts": 8, "num_envs": 2, "gamma": 1, "policy_lr_start": 0.06548824413400488, "policy_lr_end": 0.0004704992874039154, "q_lr_start": 0.0517363360590694, "q_lr_end": 5.172503184677546e-05, "alpha": 0.6380395140274236, "eta": 1.379141379818223, "autotune": false, "target_entropy_scale": 0.1, "linear_schedule": false, "__trial_index__": 1}, "time_since_restore": 142.62038731575012, "iterations_since_restore": 59}
{"reward": 9.0, "timestamp": 1711475149, "checkpoint_dir_name": null, "done": false, "training_iteration": 60, "trial_id": "a29fb57c", "date": "2024-03-26_18-45-49", "time_this_iter_s": 1.9913771152496338, "time_total_s": 144.61176443099976, "pid": 5327, "hostname": "Nicolass-Air.technicolor.net", "node_ip": "127.0.0.1", "config": {"exp_name": "QREPS", "seed": 1, "torch_deterministic": true, "cuda": true, "track": false, "wandb_project_name": "QREPS_CartPole-v1", "wandb_entity": "TFG", "capture_video": false, "env_id": "CartPole-v1", "total_timesteps": 500, "num_updates": 70, "buffer_size": 10000, "update_epochs": 10, "update_policy_epochs": 450, "num_rollouts": 8, "num_envs": 2, "gamma": 1, "policy_lr_start": 0.06548824413400488, "policy_lr_end": 0.0004704992874039154, "q_lr_start": 0.0517363360590694, "q_lr_end": 5.172503184677546e-05, "alpha": 0.6380395140274236, "eta": 1.379141379818223, "autotune": false, "target_entropy_scale": 0.1, "linear_schedule": false, "__trial_index__": 1}, "time_since_restore": 144.61176443099976, "iterations_since_restore": 60}
{"reward": 9.0, "timestamp": 1711475151, "checkpoint_dir_name": null, "done": false, "training_iteration": 61, "trial_id": "a29fb57c", "date": "2024-03-26_18-45-51", "time_this_iter_s": 2.181504011154175, "time_total_s": 146.79326844215393, "pid": 5327, "hostname": "Nicolass-Air.technicolor.net", "node_ip": "127.0.0.1", "config": {"exp_name": "QREPS", "seed": 1, "torch_deterministic": true, "cuda": true, "track": false, "wandb_project_name": "QREPS_CartPole-v1", "wandb_entity": "TFG", "capture_video": false, "env_id": "CartPole-v1", "total_timesteps": 500, "num_updates": 70, "buffer_size": 10000, "update_epochs": 10, "update_policy_epochs": 450, "num_rollouts": 8, "num_envs": 2, "gamma": 1, "policy_lr_start": 0.06548824413400488, "policy_lr_end": 0.0004704992874039154, "q_lr_start": 0.0517363360590694, "q_lr_end": 5.172503184677546e-05, "alpha": 0.6380395140274236, "eta": 1.379141379818223, "autotune": false, "target_entropy_scale": 0.1, "linear_schedule": false, "__trial_index__": 1}, "time_since_restore": 146.79326844215393, "iterations_since_restore": 61}
{"reward": 9.0, "timestamp": 1711475153, "checkpoint_dir_name": null, "done": false, "training_iteration": 62, "trial_id": "a29fb57c", "date": "2024-03-26_18-45-53", "time_this_iter_s": 1.9815659523010254, "time_total_s": 148.77483439445496, "pid": 5327, "hostname": "Nicolass-Air.technicolor.net", "node_ip": "127.0.0.1", "config": {"exp_name": "QREPS", "seed": 1, "torch_deterministic": true, "cuda": true, "track": false, "wandb_project_name": "QREPS_CartPole-v1", "wandb_entity": "TFG", "capture_video": false, "env_id": "CartPole-v1", "total_timesteps": 500, "num_updates": 70, "buffer_size": 10000, "update_epochs": 10, "update_policy_epochs": 450, "num_rollouts": 8, "num_envs": 2, "gamma": 1, "policy_lr_start": 0.06548824413400488, "policy_lr_end": 0.0004704992874039154, "q_lr_start": 0.0517363360590694, "q_lr_end": 5.172503184677546e-05, "alpha": 0.6380395140274236, "eta": 1.379141379818223, "autotune": false, "target_entropy_scale": 0.1, "linear_schedule": false, "__trial_index__": 1}, "time_since_restore": 148.77483439445496, "iterations_since_restore": 62}
{"reward": 9.0, "timestamp": 1711475155, "checkpoint_dir_name": null, "done": false, "training_iteration": 63, "trial_id": "a29fb57c", "date": "2024-03-26_18-45-55", "time_this_iter_s": 2.1737139225006104, "time_total_s": 150.94854831695557, "pid": 5327, "hostname": "Nicolass-Air.technicolor.net", "node_ip": "127.0.0.1", "config": {"exp_name": "QREPS", "seed": 1, "torch_deterministic": true, "cuda": true, "track": false, "wandb_project_name": "QREPS_CartPole-v1", "wandb_entity": "TFG", "capture_video": false, "env_id": "CartPole-v1", "total_timesteps": 500, "num_updates": 70, "buffer_size": 10000, "update_epochs": 10, "update_policy_epochs": 450, "num_rollouts": 8, "num_envs": 2, "gamma": 1, "policy_lr_start": 0.06548824413400488, "policy_lr_end": 0.0004704992874039154, "q_lr_start": 0.0517363360590694, "q_lr_end": 5.172503184677546e-05, "alpha": 0.6380395140274236, "eta": 1.379141379818223, "autotune": false, "target_entropy_scale": 0.1, "linear_schedule": false, "__trial_index__": 1}, "time_since_restore": 150.94854831695557, "iterations_since_restore": 63}
{"reward": 9.0, "timestamp": 1711475157, "checkpoint_dir_name": null, "done": false, "training_iteration": 64, "trial_id": "a29fb57c", "date": "2024-03-26_18-45-57", "time_this_iter_s": 2.0342588424682617, "time_total_s": 152.98280715942383, "pid": 5327, "hostname": "Nicolass-Air.technicolor.net", "node_ip": "127.0.0.1", "config": {"exp_name": "QREPS", "seed": 1, "torch_deterministic": true, "cuda": true, "track": false, "wandb_project_name": "QREPS_CartPole-v1", "wandb_entity": "TFG", "capture_video": false, "env_id": "CartPole-v1", "total_timesteps": 500, "num_updates": 70, "buffer_size": 10000, "update_epochs": 10, "update_policy_epochs": 450, "num_rollouts": 8, "num_envs": 2, "gamma": 1, "policy_lr_start": 0.06548824413400488, "policy_lr_end": 0.0004704992874039154, "q_lr_start": 0.0517363360590694, "q_lr_end": 5.172503184677546e-05, "alpha": 0.6380395140274236, "eta": 1.379141379818223, "autotune": false, "target_entropy_scale": 0.1, "linear_schedule": false, "__trial_index__": 1}, "time_since_restore": 152.98280715942383, "iterations_since_restore": 64}
{"reward": 9.0, "timestamp": 1711475159, "checkpoint_dir_name": null, "done": false, "training_iteration": 65, "trial_id": "a29fb57c", "date": "2024-03-26_18-45-59", "time_this_iter_s": 2.0172181129455566, "time_total_s": 155.00002527236938, "pid": 5327, "hostname": "Nicolass-Air.technicolor.net", "node_ip": "127.0.0.1", "config": {"exp_name": "QREPS", "seed": 1, "torch_deterministic": true, "cuda": true, "track": false, "wandb_project_name": "QREPS_CartPole-v1", "wandb_entity": "TFG", "capture_video": false, "env_id": "CartPole-v1", "total_timesteps": 500, "num_updates": 70, "buffer_size": 10000, "update_epochs": 10, "update_policy_epochs": 450, "num_rollouts": 8, "num_envs": 2, "gamma": 1, "policy_lr_start": 0.06548824413400488, "policy_lr_end": 0.0004704992874039154, "q_lr_start": 0.0517363360590694, "q_lr_end": 5.172503184677546e-05, "alpha": 0.6380395140274236, "eta": 1.379141379818223, "autotune": false, "target_entropy_scale": 0.1, "linear_schedule": false, "__trial_index__": 1}, "time_since_restore": 155.00002527236938, "iterations_since_restore": 65}
{"reward": 9.0, "timestamp": 1711475162, "checkpoint_dir_name": null, "done": false, "training_iteration": 66, "trial_id": "a29fb57c", "date": "2024-03-26_18-46-02", "time_this_iter_s": 2.483574151992798, "time_total_s": 157.48359942436218, "pid": 5327, "hostname": "Nicolass-Air.technicolor.net", "node_ip": "127.0.0.1", "config": {"exp_name": "QREPS", "seed": 1, "torch_deterministic": true, "cuda": true, "track": false, "wandb_project_name": "QREPS_CartPole-v1", "wandb_entity": "TFG", "capture_video": false, "env_id": "CartPole-v1", "total_timesteps": 500, "num_updates": 70, "buffer_size": 10000, "update_epochs": 10, "update_policy_epochs": 450, "num_rollouts": 8, "num_envs": 2, "gamma": 1, "policy_lr_start": 0.06548824413400488, "policy_lr_end": 0.0004704992874039154, "q_lr_start": 0.0517363360590694, "q_lr_end": 5.172503184677546e-05, "alpha": 0.6380395140274236, "eta": 1.379141379818223, "autotune": false, "target_entropy_scale": 0.1, "linear_schedule": false, "__trial_index__": 1}, "time_since_restore": 157.48359942436218, "iterations_since_restore": 66}
{"reward": 9.0, "timestamp": 1711475166, "checkpoint_dir_name": null, "done": false, "training_iteration": 67, "trial_id": "a29fb57c", "date": "2024-03-26_18-46-06", "time_this_iter_s": 2.0996551513671875, "time_total_s": 159.58325457572937, "pid": 5327, "hostname": "Nicolass-Air.technicolor.net", "node_ip": "127.0.0.1", "config": {"exp_name": "QREPS", "seed": 1, "torch_deterministic": true, "cuda": true, "track": false, "wandb_project_name": "QREPS_CartPole-v1", "wandb_entity": "TFG", "capture_video": false, "env_id": "CartPole-v1", "total_timesteps": 500, "num_updates": 70, "buffer_size": 10000, "update_epochs": 10, "update_policy_epochs": 450, "num_rollouts": 8, "num_envs": 2, "gamma": 1, "policy_lr_start": 0.06548824413400488, "policy_lr_end": 0.0004704992874039154, "q_lr_start": 0.0517363360590694, "q_lr_end": 5.172503184677546e-05, "alpha": 0.6380395140274236, "eta": 1.379141379818223, "autotune": false, "target_entropy_scale": 0.1, "linear_schedule": false, "__trial_index__": 1}, "time_since_restore": 159.58325457572937, "iterations_since_restore": 67}
{"reward": 9.0, "timestamp": 1711475168, "checkpoint_dir_name": null, "done": false, "training_iteration": 68, "trial_id": "a29fb57c", "date": "2024-03-26_18-46-08", "time_this_iter_s": 1.9657542705535889, "time_total_s": 161.54900884628296, "pid": 5327, "hostname": "Nicolass-Air.technicolor.net", "node_ip": "127.0.0.1", "config": {"exp_name": "QREPS", "seed": 1, "torch_deterministic": true, "cuda": true, "track": false, "wandb_project_name": "QREPS_CartPole-v1", "wandb_entity": "TFG", "capture_video": false, "env_id": "CartPole-v1", "total_timesteps": 500, "num_updates": 70, "buffer_size": 10000, "update_epochs": 10, "update_policy_epochs": 450, "num_rollouts": 8, "num_envs": 2, "gamma": 1, "policy_lr_start": 0.06548824413400488, "policy_lr_end": 0.0004704992874039154, "q_lr_start": 0.0517363360590694, "q_lr_end": 5.172503184677546e-05, "alpha": 0.6380395140274236, "eta": 1.379141379818223, "autotune": false, "target_entropy_scale": 0.1, "linear_schedule": false, "__trial_index__": 1}, "time_since_restore": 161.54900884628296, "iterations_since_restore": 68}
{"reward": 9.0, "timestamp": 1711475170, "checkpoint_dir_name": null, "done": false, "training_iteration": 69, "trial_id": "a29fb57c", "date": "2024-03-26_18-46-10", "time_this_iter_s": 2.029744863510132, "time_total_s": 163.5787537097931, "pid": 5327, "hostname": "Nicolass-Air.technicolor.net", "node_ip": "127.0.0.1", "config": {"exp_name": "QREPS", "seed": 1, "torch_deterministic": true, "cuda": true, "track": false, "wandb_project_name": "QREPS_CartPole-v1", "wandb_entity": "TFG", "capture_video": false, "env_id": "CartPole-v1", "total_timesteps": 500, "num_updates": 70, "buffer_size": 10000, "update_epochs": 10, "update_policy_epochs": 450, "num_rollouts": 8, "num_envs": 2, "gamma": 1, "policy_lr_start": 0.06548824413400488, "policy_lr_end": 0.0004704992874039154, "q_lr_start": 0.0517363360590694, "q_lr_end": 5.172503184677546e-05, "alpha": 0.6380395140274236, "eta": 1.379141379818223, "autotune": false, "target_entropy_scale": 0.1, "linear_schedule": false, "__trial_index__": 1}, "time_since_restore": 163.5787537097931, "iterations_since_restore": 69}
{"reward": 9.0, "timestamp": 1711475172, "checkpoint_dir_name": null, "done": false, "training_iteration": 70, "trial_id": "a29fb57c", "date": "2024-03-26_18-46-12", "time_this_iter_s": 2.2508068084716797, "time_total_s": 165.82956051826477, "pid": 5327, "hostname": "Nicolass-Air.technicolor.net", "node_ip": "127.0.0.1", "config": {"exp_name": "QREPS", "seed": 1, "torch_deterministic": true, "cuda": true, "track": false, "wandb_project_name": "QREPS_CartPole-v1", "wandb_entity": "TFG", "capture_video": false, "env_id": "CartPole-v1", "total_timesteps": 500, "num_updates": 70, "buffer_size": 10000, "update_epochs": 10, "update_policy_epochs": 450, "num_rollouts": 8, "num_envs": 2, "gamma": 1, "policy_lr_start": 0.06548824413400488, "policy_lr_end": 0.0004704992874039154, "q_lr_start": 0.0517363360590694, "q_lr_end": 5.172503184677546e-05, "alpha": 0.6380395140274236, "eta": 1.379141379818223, "autotune": false, "target_entropy_scale": 0.1, "linear_schedule": false, "__trial_index__": 1}, "time_since_restore": 165.82956051826477, "iterations_since_restore": 70}
