{"reward": 20.0, "timestamp": 1711467263, "checkpoint_dir_name": null, "done": false, "training_iteration": 1, "trial_id": "97b5cc17", "date": "2024-03-26_16-34-23", "time_this_iter_s": 1.6632158756256104, "time_total_s": 1.6632158756256104, "pid": 269, "hostname": "Nicolass-Air.technicolor.net", "node_ip": "127.0.0.1", "config": {"exp_name": "QREPS", "seed": 1, "torch_deterministic": true, "cuda": true, "track": false, "wandb_project_name": "QREPS_CartPole-v1", "wandb_entity": "TFG", "capture_video": false, "env_id": "CartPole-v1", "total_timesteps": 200, "num_updates": 40, "buffer_size": 10000, "update_epochs": 450, "update_policy_epochs": 100, "num_rollouts": 1, "num_envs": 2, "gamma": 0.99, "policy_lr_start": 0.003250226877551645, "policy_lr_end": 1.093370662985288e-05, "q_lr_start": 0.007976025327952099, "q_lr_end": 1.2534303604942787e-05, "alpha": 2.5079101787892424, "eta": 0.2672078095784446, "autotune": false, "target_entropy_scale": 0.1, "linear_schedule": false, "__trial_index__": 1}, "time_since_restore": 1.6632158756256104, "iterations_since_restore": 1}
{"reward": 57.0, "timestamp": 1711467266, "checkpoint_dir_name": null, "done": false, "training_iteration": 2, "trial_id": "97b5cc17", "date": "2024-03-26_16-34-26", "time_this_iter_s": 2.4170851707458496, "time_total_s": 4.08030104637146, "pid": 269, "hostname": "Nicolass-Air.technicolor.net", "node_ip": "127.0.0.1", "config": {"exp_name": "QREPS", "seed": 1, "torch_deterministic": true, "cuda": true, "track": false, "wandb_project_name": "QREPS_CartPole-v1", "wandb_entity": "TFG", "capture_video": false, "env_id": "CartPole-v1", "total_timesteps": 200, "num_updates": 40, "buffer_size": 10000, "update_epochs": 450, "update_policy_epochs": 100, "num_rollouts": 1, "num_envs": 2, "gamma": 0.99, "policy_lr_start": 0.003250226877551645, "policy_lr_end": 1.093370662985288e-05, "q_lr_start": 0.007976025327952099, "q_lr_end": 1.2534303604942787e-05, "alpha": 2.5079101787892424, "eta": 0.2672078095784446, "autotune": false, "target_entropy_scale": 0.1, "linear_schedule": false, "__trial_index__": 1}, "time_since_restore": 4.08030104637146, "iterations_since_restore": 2}
{"reward": 56.0, "timestamp": 1711467268, "checkpoint_dir_name": null, "done": false, "training_iteration": 3, "trial_id": "97b5cc17", "date": "2024-03-26_16-34-28", "time_this_iter_s": 2.8764278888702393, "time_total_s": 6.956728935241699, "pid": 269, "hostname": "Nicolass-Air.technicolor.net", "node_ip": "127.0.0.1", "config": {"exp_name": "QREPS", "seed": 1, "torch_deterministic": true, "cuda": true, "track": false, "wandb_project_name": "QREPS_CartPole-v1", "wandb_entity": "TFG", "capture_video": false, "env_id": "CartPole-v1", "total_timesteps": 200, "num_updates": 40, "buffer_size": 10000, "update_epochs": 450, "update_policy_epochs": 100, "num_rollouts": 1, "num_envs": 2, "gamma": 0.99, "policy_lr_start": 0.003250226877551645, "policy_lr_end": 1.093370662985288e-05, "q_lr_start": 0.007976025327952099, "q_lr_end": 1.2534303604942787e-05, "alpha": 2.5079101787892424, "eta": 0.2672078095784446, "autotune": false, "target_entropy_scale": 0.1, "linear_schedule": false, "__trial_index__": 1}, "time_since_restore": 6.956728935241699, "iterations_since_restore": 3}
{"reward": 72.0, "timestamp": 1711467272, "checkpoint_dir_name": null, "done": false, "training_iteration": 4, "trial_id": "97b5cc17", "date": "2024-03-26_16-34-32", "time_this_iter_s": 3.1128971576690674, "time_total_s": 10.069626092910767, "pid": 269, "hostname": "Nicolass-Air.technicolor.net", "node_ip": "127.0.0.1", "config": {"exp_name": "QREPS", "seed": 1, "torch_deterministic": true, "cuda": true, "track": false, "wandb_project_name": "QREPS_CartPole-v1", "wandb_entity": "TFG", "capture_video": false, "env_id": "CartPole-v1", "total_timesteps": 200, "num_updates": 40, "buffer_size": 10000, "update_epochs": 450, "update_policy_epochs": 100, "num_rollouts": 1, "num_envs": 2, "gamma": 0.99, "policy_lr_start": 0.003250226877551645, "policy_lr_end": 1.093370662985288e-05, "q_lr_start": 0.007976025327952099, "q_lr_end": 1.2534303604942787e-05, "alpha": 2.5079101787892424, "eta": 0.2672078095784446, "autotune": false, "target_entropy_scale": 0.1, "linear_schedule": false, "__trial_index__": 1}, "time_since_restore": 10.069626092910767, "iterations_since_restore": 4}
{"reward": 63.0, "timestamp": 1711467275, "checkpoint_dir_name": null, "done": false, "training_iteration": 5, "trial_id": "97b5cc17", "date": "2024-03-26_16-34-35", "time_this_iter_s": 3.060934066772461, "time_total_s": 13.130560159683228, "pid": 269, "hostname": "Nicolass-Air.technicolor.net", "node_ip": "127.0.0.1", "config": {"exp_name": "QREPS", "seed": 1, "torch_deterministic": true, "cuda": true, "track": false, "wandb_project_name": "QREPS_CartPole-v1", "wandb_entity": "TFG", "capture_video": false, "env_id": "CartPole-v1", "total_timesteps": 200, "num_updates": 40, "buffer_size": 10000, "update_epochs": 450, "update_policy_epochs": 100, "num_rollouts": 1, "num_envs": 2, "gamma": 0.99, "policy_lr_start": 0.003250226877551645, "policy_lr_end": 1.093370662985288e-05, "q_lr_start": 0.007976025327952099, "q_lr_end": 1.2534303604942787e-05, "alpha": 2.5079101787892424, "eta": 0.2672078095784446, "autotune": false, "target_entropy_scale": 0.1, "linear_schedule": false, "__trial_index__": 1}, "time_since_restore": 13.130560159683228, "iterations_since_restore": 5}
{"reward": 60.0, "timestamp": 1711467277, "checkpoint_dir_name": null, "done": false, "training_iteration": 6, "trial_id": "97b5cc17", "date": "2024-03-26_16-34-37", "time_this_iter_s": 2.8721508979797363, "time_total_s": 16.002711057662964, "pid": 269, "hostname": "Nicolass-Air.technicolor.net", "node_ip": "127.0.0.1", "config": {"exp_name": "QREPS", "seed": 1, "torch_deterministic": true, "cuda": true, "track": false, "wandb_project_name": "QREPS_CartPole-v1", "wandb_entity": "TFG", "capture_video": false, "env_id": "CartPole-v1", "total_timesteps": 200, "num_updates": 40, "buffer_size": 10000, "update_epochs": 450, "update_policy_epochs": 100, "num_rollouts": 1, "num_envs": 2, "gamma": 0.99, "policy_lr_start": 0.003250226877551645, "policy_lr_end": 1.093370662985288e-05, "q_lr_start": 0.007976025327952099, "q_lr_end": 1.2534303604942787e-05, "alpha": 2.5079101787892424, "eta": 0.2672078095784446, "autotune": false, "target_entropy_scale": 0.1, "linear_schedule": false, "__trial_index__": 1}, "time_since_restore": 16.002711057662964, "iterations_since_restore": 6}
{"reward": 58.0, "timestamp": 1711467280, "checkpoint_dir_name": null, "done": false, "training_iteration": 7, "trial_id": "97b5cc17", "date": "2024-03-26_16-34-40", "time_this_iter_s": 2.8929479122161865, "time_total_s": 18.89565896987915, "pid": 269, "hostname": "Nicolass-Air.technicolor.net", "node_ip": "127.0.0.1", "config": {"exp_name": "QREPS", "seed": 1, "torch_deterministic": true, "cuda": true, "track": false, "wandb_project_name": "QREPS_CartPole-v1", "wandb_entity": "TFG", "capture_video": false, "env_id": "CartPole-v1", "total_timesteps": 200, "num_updates": 40, "buffer_size": 10000, "update_epochs": 450, "update_policy_epochs": 100, "num_rollouts": 1, "num_envs": 2, "gamma": 0.99, "policy_lr_start": 0.003250226877551645, "policy_lr_end": 1.093370662985288e-05, "q_lr_start": 0.007976025327952099, "q_lr_end": 1.2534303604942787e-05, "alpha": 2.5079101787892424, "eta": 0.2672078095784446, "autotune": false, "target_entropy_scale": 0.1, "linear_schedule": false, "__trial_index__": 1}, "time_since_restore": 18.89565896987915, "iterations_since_restore": 7}
{"reward": 61.0, "timestamp": 1711467283, "checkpoint_dir_name": null, "done": false, "training_iteration": 8, "trial_id": "97b5cc17", "date": "2024-03-26_16-34-43", "time_this_iter_s": 2.9441819190979004, "time_total_s": 21.83984088897705, "pid": 269, "hostname": "Nicolass-Air.technicolor.net", "node_ip": "127.0.0.1", "config": {"exp_name": "QREPS", "seed": 1, "torch_deterministic": true, "cuda": true, "track": false, "wandb_project_name": "QREPS_CartPole-v1", "wandb_entity": "TFG", "capture_video": false, "env_id": "CartPole-v1", "total_timesteps": 200, "num_updates": 40, "buffer_size": 10000, "update_epochs": 450, "update_policy_epochs": 100, "num_rollouts": 1, "num_envs": 2, "gamma": 0.99, "policy_lr_start": 0.003250226877551645, "policy_lr_end": 1.093370662985288e-05, "q_lr_start": 0.007976025327952099, "q_lr_end": 1.2534303604942787e-05, "alpha": 2.5079101787892424, "eta": 0.2672078095784446, "autotune": false, "target_entropy_scale": 0.1, "linear_schedule": false, "__trial_index__": 1}, "time_since_restore": 21.83984088897705, "iterations_since_restore": 8}
{"reward": 58.0, "timestamp": 1711467286, "checkpoint_dir_name": null, "done": false, "training_iteration": 9, "trial_id": "97b5cc17", "date": "2024-03-26_16-34-46", "time_this_iter_s": 2.9406111240386963, "time_total_s": 24.780452013015747, "pid": 269, "hostname": "Nicolass-Air.technicolor.net", "node_ip": "127.0.0.1", "config": {"exp_name": "QREPS", "seed": 1, "torch_deterministic": true, "cuda": true, "track": false, "wandb_project_name": "QREPS_CartPole-v1", "wandb_entity": "TFG", "capture_video": false, "env_id": "CartPole-v1", "total_timesteps": 200, "num_updates": 40, "buffer_size": 10000, "update_epochs": 450, "update_policy_epochs": 100, "num_rollouts": 1, "num_envs": 2, "gamma": 0.99, "policy_lr_start": 0.003250226877551645, "policy_lr_end": 1.093370662985288e-05, "q_lr_start": 0.007976025327952099, "q_lr_end": 1.2534303604942787e-05, "alpha": 2.5079101787892424, "eta": 0.2672078095784446, "autotune": false, "target_entropy_scale": 0.1, "linear_schedule": false, "__trial_index__": 1}, "time_since_restore": 24.780452013015747, "iterations_since_restore": 9}
{"reward": 63.0, "timestamp": 1711467289, "checkpoint_dir_name": null, "done": false, "training_iteration": 10, "trial_id": "97b5cc17", "date": "2024-03-26_16-34-49", "time_this_iter_s": 2.8128089904785156, "time_total_s": 27.593261003494263, "pid": 269, "hostname": "Nicolass-Air.technicolor.net", "node_ip": "127.0.0.1", "config": {"exp_name": "QREPS", "seed": 1, "torch_deterministic": true, "cuda": true, "track": false, "wandb_project_name": "QREPS_CartPole-v1", "wandb_entity": "TFG", "capture_video": false, "env_id": "CartPole-v1", "total_timesteps": 200, "num_updates": 40, "buffer_size": 10000, "update_epochs": 450, "update_policy_epochs": 100, "num_rollouts": 1, "num_envs": 2, "gamma": 0.99, "policy_lr_start": 0.003250226877551645, "policy_lr_end": 1.093370662985288e-05, "q_lr_start": 0.007976025327952099, "q_lr_end": 1.2534303604942787e-05, "alpha": 2.5079101787892424, "eta": 0.2672078095784446, "autotune": false, "target_entropy_scale": 0.1, "linear_schedule": false, "__trial_index__": 1}, "time_since_restore": 27.593261003494263, "iterations_since_restore": 10}
{"reward": 60.0, "timestamp": 1711467292, "checkpoint_dir_name": null, "done": false, "training_iteration": 11, "trial_id": "97b5cc17", "date": "2024-03-26_16-34-52", "time_this_iter_s": 2.9562759399414062, "time_total_s": 30.54953694343567, "pid": 269, "hostname": "Nicolass-Air.technicolor.net", "node_ip": "127.0.0.1", "config": {"exp_name": "QREPS", "seed": 1, "torch_deterministic": true, "cuda": true, "track": false, "wandb_project_name": "QREPS_CartPole-v1", "wandb_entity": "TFG", "capture_video": false, "env_id": "CartPole-v1", "total_timesteps": 200, "num_updates": 40, "buffer_size": 10000, "update_epochs": 450, "update_policy_epochs": 100, "num_rollouts": 1, "num_envs": 2, "gamma": 0.99, "policy_lr_start": 0.003250226877551645, "policy_lr_end": 1.093370662985288e-05, "q_lr_start": 0.007976025327952099, "q_lr_end": 1.2534303604942787e-05, "alpha": 2.5079101787892424, "eta": 0.2672078095784446, "autotune": false, "target_entropy_scale": 0.1, "linear_schedule": false, "__trial_index__": 1}, "time_since_restore": 30.54953694343567, "iterations_since_restore": 11}
{"reward": 65.0, "timestamp": 1711467295, "checkpoint_dir_name": null, "done": false, "training_iteration": 12, "trial_id": "97b5cc17", "date": "2024-03-26_16-34-55", "time_this_iter_s": 3.1218738555908203, "time_total_s": 33.67141079902649, "pid": 269, "hostname": "Nicolass-Air.technicolor.net", "node_ip": "127.0.0.1", "config": {"exp_name": "QREPS", "seed": 1, "torch_deterministic": true, "cuda": true, "track": false, "wandb_project_name": "QREPS_CartPole-v1", "wandb_entity": "TFG", "capture_video": false, "env_id": "CartPole-v1", "total_timesteps": 200, "num_updates": 40, "buffer_size": 10000, "update_epochs": 450, "update_policy_epochs": 100, "num_rollouts": 1, "num_envs": 2, "gamma": 0.99, "policy_lr_start": 0.003250226877551645, "policy_lr_end": 1.093370662985288e-05, "q_lr_start": 0.007976025327952099, "q_lr_end": 1.2534303604942787e-05, "alpha": 2.5079101787892424, "eta": 0.2672078095784446, "autotune": false, "target_entropy_scale": 0.1, "linear_schedule": false, "__trial_index__": 1}, "time_since_restore": 33.67141079902649, "iterations_since_restore": 12}
{"reward": 65.0, "timestamp": 1711467298, "checkpoint_dir_name": null, "done": false, "training_iteration": 13, "trial_id": "97b5cc17", "date": "2024-03-26_16-34-58", "time_this_iter_s": 3.2221970558166504, "time_total_s": 36.89360785484314, "pid": 269, "hostname": "Nicolass-Air.technicolor.net", "node_ip": "127.0.0.1", "config": {"exp_name": "QREPS", "seed": 1, "torch_deterministic": true, "cuda": true, "track": false, "wandb_project_name": "QREPS_CartPole-v1", "wandb_entity": "TFG", "capture_video": false, "env_id": "CartPole-v1", "total_timesteps": 200, "num_updates": 40, "buffer_size": 10000, "update_epochs": 450, "update_policy_epochs": 100, "num_rollouts": 1, "num_envs": 2, "gamma": 0.99, "policy_lr_start": 0.003250226877551645, "policy_lr_end": 1.093370662985288e-05, "q_lr_start": 0.007976025327952099, "q_lr_end": 1.2534303604942787e-05, "alpha": 2.5079101787892424, "eta": 0.2672078095784446, "autotune": false, "target_entropy_scale": 0.1, "linear_schedule": false, "__trial_index__": 1}, "time_since_restore": 36.89360785484314, "iterations_since_restore": 13}
{"reward": 65.0, "timestamp": 1711467302, "checkpoint_dir_name": null, "done": false, "training_iteration": 14, "trial_id": "97b5cc17", "date": "2024-03-26_16-35-02", "time_this_iter_s": 3.1218409538269043, "time_total_s": 40.015448808670044, "pid": 269, "hostname": "Nicolass-Air.technicolor.net", "node_ip": "127.0.0.1", "config": {"exp_name": "QREPS", "seed": 1, "torch_deterministic": true, "cuda": true, "track": false, "wandb_project_name": "QREPS_CartPole-v1", "wandb_entity": "TFG", "capture_video": false, "env_id": "CartPole-v1", "total_timesteps": 200, "num_updates": 40, "buffer_size": 10000, "update_epochs": 450, "update_policy_epochs": 100, "num_rollouts": 1, "num_envs": 2, "gamma": 0.99, "policy_lr_start": 0.003250226877551645, "policy_lr_end": 1.093370662985288e-05, "q_lr_start": 0.007976025327952099, "q_lr_end": 1.2534303604942787e-05, "alpha": 2.5079101787892424, "eta": 0.2672078095784446, "autotune": false, "target_entropy_scale": 0.1, "linear_schedule": false, "__trial_index__": 1}, "time_since_restore": 40.015448808670044, "iterations_since_restore": 14}
{"reward": 61.0, "timestamp": 1711467306, "checkpoint_dir_name": null, "done": false, "training_iteration": 15, "trial_id": "97b5cc17", "date": "2024-03-26_16-35-06", "time_this_iter_s": 3.220963954925537, "time_total_s": 43.23641276359558, "pid": 269, "hostname": "Nicolass-Air.technicolor.net", "node_ip": "127.0.0.1", "config": {"exp_name": "QREPS", "seed": 1, "torch_deterministic": true, "cuda": true, "track": false, "wandb_project_name": "QREPS_CartPole-v1", "wandb_entity": "TFG", "capture_video": false, "env_id": "CartPole-v1", "total_timesteps": 200, "num_updates": 40, "buffer_size": 10000, "update_epochs": 450, "update_policy_epochs": 100, "num_rollouts": 1, "num_envs": 2, "gamma": 0.99, "policy_lr_start": 0.003250226877551645, "policy_lr_end": 1.093370662985288e-05, "q_lr_start": 0.007976025327952099, "q_lr_end": 1.2534303604942787e-05, "alpha": 2.5079101787892424, "eta": 0.2672078095784446, "autotune": false, "target_entropy_scale": 0.1, "linear_schedule": false, "__trial_index__": 1}, "time_since_restore": 43.23641276359558, "iterations_since_restore": 15}
{"reward": 61.0, "timestamp": 1711467309, "checkpoint_dir_name": null, "done": false, "training_iteration": 16, "trial_id": "97b5cc17", "date": "2024-03-26_16-35-09", "time_this_iter_s": 2.9951748847961426, "time_total_s": 46.231587648391724, "pid": 269, "hostname": "Nicolass-Air.technicolor.net", "node_ip": "127.0.0.1", "config": {"exp_name": "QREPS", "seed": 1, "torch_deterministic": true, "cuda": true, "track": false, "wandb_project_name": "QREPS_CartPole-v1", "wandb_entity": "TFG", "capture_video": false, "env_id": "CartPole-v1", "total_timesteps": 200, "num_updates": 40, "buffer_size": 10000, "update_epochs": 450, "update_policy_epochs": 100, "num_rollouts": 1, "num_envs": 2, "gamma": 0.99, "policy_lr_start": 0.003250226877551645, "policy_lr_end": 1.093370662985288e-05, "q_lr_start": 0.007976025327952099, "q_lr_end": 1.2534303604942787e-05, "alpha": 2.5079101787892424, "eta": 0.2672078095784446, "autotune": false, "target_entropy_scale": 0.1, "linear_schedule": false, "__trial_index__": 1}, "time_since_restore": 46.231587648391724, "iterations_since_restore": 16}
{"reward": 61.0, "timestamp": 1711467312, "checkpoint_dir_name": null, "done": false, "training_iteration": 17, "trial_id": "97b5cc17", "date": "2024-03-26_16-35-12", "time_this_iter_s": 3.0875067710876465, "time_total_s": 49.31909441947937, "pid": 269, "hostname": "Nicolass-Air.technicolor.net", "node_ip": "127.0.0.1", "config": {"exp_name": "QREPS", "seed": 1, "torch_deterministic": true, "cuda": true, "track": false, "wandb_project_name": "QREPS_CartPole-v1", "wandb_entity": "TFG", "capture_video": false, "env_id": "CartPole-v1", "total_timesteps": 200, "num_updates": 40, "buffer_size": 10000, "update_epochs": 450, "update_policy_epochs": 100, "num_rollouts": 1, "num_envs": 2, "gamma": 0.99, "policy_lr_start": 0.003250226877551645, "policy_lr_end": 1.093370662985288e-05, "q_lr_start": 0.007976025327952099, "q_lr_end": 1.2534303604942787e-05, "alpha": 2.5079101787892424, "eta": 0.2672078095784446, "autotune": false, "target_entropy_scale": 0.1, "linear_schedule": false, "__trial_index__": 1}, "time_since_restore": 49.31909441947937, "iterations_since_restore": 17}
{"reward": 61.0, "timestamp": 1711467315, "checkpoint_dir_name": null, "done": false, "training_iteration": 18, "trial_id": "97b5cc17", "date": "2024-03-26_16-35-15", "time_this_iter_s": 3.189918279647827, "time_total_s": 52.5090126991272, "pid": 269, "hostname": "Nicolass-Air.technicolor.net", "node_ip": "127.0.0.1", "config": {"exp_name": "QREPS", "seed": 1, "torch_deterministic": true, "cuda": true, "track": false, "wandb_project_name": "QREPS_CartPole-v1", "wandb_entity": "TFG", "capture_video": false, "env_id": "CartPole-v1", "total_timesteps": 200, "num_updates": 40, "buffer_size": 10000, "update_epochs": 450, "update_policy_epochs": 100, "num_rollouts": 1, "num_envs": 2, "gamma": 0.99, "policy_lr_start": 0.003250226877551645, "policy_lr_end": 1.093370662985288e-05, "q_lr_start": 0.007976025327952099, "q_lr_end": 1.2534303604942787e-05, "alpha": 2.5079101787892424, "eta": 0.2672078095784446, "autotune": false, "target_entropy_scale": 0.1, "linear_schedule": false, "__trial_index__": 1}, "time_since_restore": 52.5090126991272, "iterations_since_restore": 18}
{"reward": 61.0, "timestamp": 1711467318, "checkpoint_dir_name": null, "done": false, "training_iteration": 19, "trial_id": "97b5cc17", "date": "2024-03-26_16-35-18", "time_this_iter_s": 3.175813913345337, "time_total_s": 55.684826612472534, "pid": 269, "hostname": "Nicolass-Air.technicolor.net", "node_ip": "127.0.0.1", "config": {"exp_name": "QREPS", "seed": 1, "torch_deterministic": true, "cuda": true, "track": false, "wandb_project_name": "QREPS_CartPole-v1", "wandb_entity": "TFG", "capture_video": false, "env_id": "CartPole-v1", "total_timesteps": 200, "num_updates": 40, "buffer_size": 10000, "update_epochs": 450, "update_policy_epochs": 100, "num_rollouts": 1, "num_envs": 2, "gamma": 0.99, "policy_lr_start": 0.003250226877551645, "policy_lr_end": 1.093370662985288e-05, "q_lr_start": 0.007976025327952099, "q_lr_end": 1.2534303604942787e-05, "alpha": 2.5079101787892424, "eta": 0.2672078095784446, "autotune": false, "target_entropy_scale": 0.1, "linear_schedule": false, "__trial_index__": 1}, "time_since_restore": 55.684826612472534, "iterations_since_restore": 19}
{"reward": 61.0, "timestamp": 1711467321, "checkpoint_dir_name": null, "done": false, "training_iteration": 20, "trial_id": "97b5cc17", "date": "2024-03-26_16-35-21", "time_this_iter_s": 2.975964307785034, "time_total_s": 58.66079092025757, "pid": 269, "hostname": "Nicolass-Air.technicolor.net", "node_ip": "127.0.0.1", "config": {"exp_name": "QREPS", "seed": 1, "torch_deterministic": true, "cuda": true, "track": false, "wandb_project_name": "QREPS_CartPole-v1", "wandb_entity": "TFG", "capture_video": false, "env_id": "CartPole-v1", "total_timesteps": 200, "num_updates": 40, "buffer_size": 10000, "update_epochs": 450, "update_policy_epochs": 100, "num_rollouts": 1, "num_envs": 2, "gamma": 0.99, "policy_lr_start": 0.003250226877551645, "policy_lr_end": 1.093370662985288e-05, "q_lr_start": 0.007976025327952099, "q_lr_end": 1.2534303604942787e-05, "alpha": 2.5079101787892424, "eta": 0.2672078095784446, "autotune": false, "target_entropy_scale": 0.1, "linear_schedule": false, "__trial_index__": 1}, "time_since_restore": 58.66079092025757, "iterations_since_restore": 20}
{"reward": 61.0, "timestamp": 1711467325, "checkpoint_dir_name": null, "done": false, "training_iteration": 21, "trial_id": "97b5cc17", "date": "2024-03-26_16-35-25", "time_this_iter_s": 3.127384901046753, "time_total_s": 61.78817582130432, "pid": 269, "hostname": "Nicolass-Air.technicolor.net", "node_ip": "127.0.0.1", "config": {"exp_name": "QREPS", "seed": 1, "torch_deterministic": true, "cuda": true, "track": false, "wandb_project_name": "QREPS_CartPole-v1", "wandb_entity": "TFG", "capture_video": false, "env_id": "CartPole-v1", "total_timesteps": 200, "num_updates": 40, "buffer_size": 10000, "update_epochs": 450, "update_policy_epochs": 100, "num_rollouts": 1, "num_envs": 2, "gamma": 0.99, "policy_lr_start": 0.003250226877551645, "policy_lr_end": 1.093370662985288e-05, "q_lr_start": 0.007976025327952099, "q_lr_end": 1.2534303604942787e-05, "alpha": 2.5079101787892424, "eta": 0.2672078095784446, "autotune": false, "target_entropy_scale": 0.1, "linear_schedule": false, "__trial_index__": 1}, "time_since_restore": 61.78817582130432, "iterations_since_restore": 21}
{"reward": 61.0, "timestamp": 1711467328, "checkpoint_dir_name": null, "done": false, "training_iteration": 22, "trial_id": "97b5cc17", "date": "2024-03-26_16-35-28", "time_this_iter_s": 3.1373889446258545, "time_total_s": 64.92556476593018, "pid": 269, "hostname": "Nicolass-Air.technicolor.net", "node_ip": "127.0.0.1", "config": {"exp_name": "QREPS", "seed": 1, "torch_deterministic": true, "cuda": true, "track": false, "wandb_project_name": "QREPS_CartPole-v1", "wandb_entity": "TFG", "capture_video": false, "env_id": "CartPole-v1", "total_timesteps": 200, "num_updates": 40, "buffer_size": 10000, "update_epochs": 450, "update_policy_epochs": 100, "num_rollouts": 1, "num_envs": 2, "gamma": 0.99, "policy_lr_start": 0.003250226877551645, "policy_lr_end": 1.093370662985288e-05, "q_lr_start": 0.007976025327952099, "q_lr_end": 1.2534303604942787e-05, "alpha": 2.5079101787892424, "eta": 0.2672078095784446, "autotune": false, "target_entropy_scale": 0.1, "linear_schedule": false, "__trial_index__": 1}, "time_since_restore": 64.92556476593018, "iterations_since_restore": 22}
{"reward": 61.0, "timestamp": 1711467331, "checkpoint_dir_name": null, "done": false, "training_iteration": 23, "trial_id": "97b5cc17", "date": "2024-03-26_16-35-31", "time_this_iter_s": 3.2310950756073, "time_total_s": 68.15665984153748, "pid": 269, "hostname": "Nicolass-Air.technicolor.net", "node_ip": "127.0.0.1", "config": {"exp_name": "QREPS", "seed": 1, "torch_deterministic": true, "cuda": true, "track": false, "wandb_project_name": "QREPS_CartPole-v1", "wandb_entity": "TFG", "capture_video": false, "env_id": "CartPole-v1", "total_timesteps": 200, "num_updates": 40, "buffer_size": 10000, "update_epochs": 450, "update_policy_epochs": 100, "num_rollouts": 1, "num_envs": 2, "gamma": 0.99, "policy_lr_start": 0.003250226877551645, "policy_lr_end": 1.093370662985288e-05, "q_lr_start": 0.007976025327952099, "q_lr_end": 1.2534303604942787e-05, "alpha": 2.5079101787892424, "eta": 0.2672078095784446, "autotune": false, "target_entropy_scale": 0.1, "linear_schedule": false, "__trial_index__": 1}, "time_since_restore": 68.15665984153748, "iterations_since_restore": 23}
{"reward": 61.0, "timestamp": 1711467334, "checkpoint_dir_name": null, "done": false, "training_iteration": 24, "trial_id": "97b5cc17", "date": "2024-03-26_16-35-34", "time_this_iter_s": 3.1352341175079346, "time_total_s": 71.29189395904541, "pid": 269, "hostname": "Nicolass-Air.technicolor.net", "node_ip": "127.0.0.1", "config": {"exp_name": "QREPS", "seed": 1, "torch_deterministic": true, "cuda": true, "track": false, "wandb_project_name": "QREPS_CartPole-v1", "wandb_entity": "TFG", "capture_video": false, "env_id": "CartPole-v1", "total_timesteps": 200, "num_updates": 40, "buffer_size": 10000, "update_epochs": 450, "update_policy_epochs": 100, "num_rollouts": 1, "num_envs": 2, "gamma": 0.99, "policy_lr_start": 0.003250226877551645, "policy_lr_end": 1.093370662985288e-05, "q_lr_start": 0.007976025327952099, "q_lr_end": 1.2534303604942787e-05, "alpha": 2.5079101787892424, "eta": 0.2672078095784446, "autotune": false, "target_entropy_scale": 0.1, "linear_schedule": false, "__trial_index__": 1}, "time_since_restore": 71.29189395904541, "iterations_since_restore": 24}
{"reward": 61.0, "timestamp": 1711467337, "checkpoint_dir_name": null, "done": false, "training_iteration": 25, "trial_id": "97b5cc17", "date": "2024-03-26_16-35-37", "time_this_iter_s": 3.238461971282959, "time_total_s": 74.53035593032837, "pid": 269, "hostname": "Nicolass-Air.technicolor.net", "node_ip": "127.0.0.1", "config": {"exp_name": "QREPS", "seed": 1, "torch_deterministic": true, "cuda": true, "track": false, "wandb_project_name": "QREPS_CartPole-v1", "wandb_entity": "TFG", "capture_video": false, "env_id": "CartPole-v1", "total_timesteps": 200, "num_updates": 40, "buffer_size": 10000, "update_epochs": 450, "update_policy_epochs": 100, "num_rollouts": 1, "num_envs": 2, "gamma": 0.99, "policy_lr_start": 0.003250226877551645, "policy_lr_end": 1.093370662985288e-05, "q_lr_start": 0.007976025327952099, "q_lr_end": 1.2534303604942787e-05, "alpha": 2.5079101787892424, "eta": 0.2672078095784446, "autotune": false, "target_entropy_scale": 0.1, "linear_schedule": false, "__trial_index__": 1}, "time_since_restore": 74.53035593032837, "iterations_since_restore": 25}
{"reward": 61.0, "timestamp": 1711467340, "checkpoint_dir_name": null, "done": false, "training_iteration": 26, "trial_id": "97b5cc17", "date": "2024-03-26_16-35-40", "time_this_iter_s": 3.1795430183410645, "time_total_s": 77.70989894866943, "pid": 269, "hostname": "Nicolass-Air.technicolor.net", "node_ip": "127.0.0.1", "config": {"exp_name": "QREPS", "seed": 1, "torch_deterministic": true, "cuda": true, "track": false, "wandb_project_name": "QREPS_CartPole-v1", "wandb_entity": "TFG", "capture_video": false, "env_id": "CartPole-v1", "total_timesteps": 200, "num_updates": 40, "buffer_size": 10000, "update_epochs": 450, "update_policy_epochs": 100, "num_rollouts": 1, "num_envs": 2, "gamma": 0.99, "policy_lr_start": 0.003250226877551645, "policy_lr_end": 1.093370662985288e-05, "q_lr_start": 0.007976025327952099, "q_lr_end": 1.2534303604942787e-05, "alpha": 2.5079101787892424, "eta": 0.2672078095784446, "autotune": false, "target_entropy_scale": 0.1, "linear_schedule": false, "__trial_index__": 1}, "time_since_restore": 77.70989894866943, "iterations_since_restore": 26}
{"reward": 61.0, "timestamp": 1711467344, "checkpoint_dir_name": null, "done": false, "training_iteration": 27, "trial_id": "97b5cc17", "date": "2024-03-26_16-35-44", "time_this_iter_s": 3.061925172805786, "time_total_s": 80.77182412147522, "pid": 269, "hostname": "Nicolass-Air.technicolor.net", "node_ip": "127.0.0.1", "config": {"exp_name": "QREPS", "seed": 1, "torch_deterministic": true, "cuda": true, "track": false, "wandb_project_name": "QREPS_CartPole-v1", "wandb_entity": "TFG", "capture_video": false, "env_id": "CartPole-v1", "total_timesteps": 200, "num_updates": 40, "buffer_size": 10000, "update_epochs": 450, "update_policy_epochs": 100, "num_rollouts": 1, "num_envs": 2, "gamma": 0.99, "policy_lr_start": 0.003250226877551645, "policy_lr_end": 1.093370662985288e-05, "q_lr_start": 0.007976025327952099, "q_lr_end": 1.2534303604942787e-05, "alpha": 2.5079101787892424, "eta": 0.2672078095784446, "autotune": false, "target_entropy_scale": 0.1, "linear_schedule": false, "__trial_index__": 1}, "time_since_restore": 80.77182412147522, "iterations_since_restore": 27}
{"reward": 61.0, "timestamp": 1711467347, "checkpoint_dir_name": null, "done": false, "training_iteration": 28, "trial_id": "97b5cc17", "date": "2024-03-26_16-35-47", "time_this_iter_s": 3.2253592014312744, "time_total_s": 83.9971833229065, "pid": 269, "hostname": "Nicolass-Air.technicolor.net", "node_ip": "127.0.0.1", "config": {"exp_name": "QREPS", "seed": 1, "torch_deterministic": true, "cuda": true, "track": false, "wandb_project_name": "QREPS_CartPole-v1", "wandb_entity": "TFG", "capture_video": false, "env_id": "CartPole-v1", "total_timesteps": 200, "num_updates": 40, "buffer_size": 10000, "update_epochs": 450, "update_policy_epochs": 100, "num_rollouts": 1, "num_envs": 2, "gamma": 0.99, "policy_lr_start": 0.003250226877551645, "policy_lr_end": 1.093370662985288e-05, "q_lr_start": 0.007976025327952099, "q_lr_end": 1.2534303604942787e-05, "alpha": 2.5079101787892424, "eta": 0.2672078095784446, "autotune": false, "target_entropy_scale": 0.1, "linear_schedule": false, "__trial_index__": 1}, "time_since_restore": 83.9971833229065, "iterations_since_restore": 28}
{"reward": 61.0, "timestamp": 1711467350, "checkpoint_dir_name": null, "done": false, "training_iteration": 29, "trial_id": "97b5cc17", "date": "2024-03-26_16-35-50", "time_this_iter_s": 3.1703531742095947, "time_total_s": 87.16753649711609, "pid": 269, "hostname": "Nicolass-Air.technicolor.net", "node_ip": "127.0.0.1", "config": {"exp_name": "QREPS", "seed": 1, "torch_deterministic": true, "cuda": true, "track": false, "wandb_project_name": "QREPS_CartPole-v1", "wandb_entity": "TFG", "capture_video": false, "env_id": "CartPole-v1", "total_timesteps": 200, "num_updates": 40, "buffer_size": 10000, "update_epochs": 450, "update_policy_epochs": 100, "num_rollouts": 1, "num_envs": 2, "gamma": 0.99, "policy_lr_start": 0.003250226877551645, "policy_lr_end": 1.093370662985288e-05, "q_lr_start": 0.007976025327952099, "q_lr_end": 1.2534303604942787e-05, "alpha": 2.5079101787892424, "eta": 0.2672078095784446, "autotune": false, "target_entropy_scale": 0.1, "linear_schedule": false, "__trial_index__": 1}, "time_since_restore": 87.16753649711609, "iterations_since_restore": 29}
{"reward": 61.0, "timestamp": 1711467353, "checkpoint_dir_name": null, "done": false, "training_iteration": 30, "trial_id": "97b5cc17", "date": "2024-03-26_16-35-53", "time_this_iter_s": 3.2083537578582764, "time_total_s": 90.37589025497437, "pid": 269, "hostname": "Nicolass-Air.technicolor.net", "node_ip": "127.0.0.1", "config": {"exp_name": "QREPS", "seed": 1, "torch_deterministic": true, "cuda": true, "track": false, "wandb_project_name": "QREPS_CartPole-v1", "wandb_entity": "TFG", "capture_video": false, "env_id": "CartPole-v1", "total_timesteps": 200, "num_updates": 40, "buffer_size": 10000, "update_epochs": 450, "update_policy_epochs": 100, "num_rollouts": 1, "num_envs": 2, "gamma": 0.99, "policy_lr_start": 0.003250226877551645, "policy_lr_end": 1.093370662985288e-05, "q_lr_start": 0.007976025327952099, "q_lr_end": 1.2534303604942787e-05, "alpha": 2.5079101787892424, "eta": 0.2672078095784446, "autotune": false, "target_entropy_scale": 0.1, "linear_schedule": false, "__trial_index__": 1}, "time_since_restore": 90.37589025497437, "iterations_since_restore": 30}
{"reward": 61.0, "timestamp": 1711467356, "checkpoint_dir_name": null, "done": false, "training_iteration": 31, "trial_id": "97b5cc17", "date": "2024-03-26_16-35-56", "time_this_iter_s": 3.308032989501953, "time_total_s": 93.68392324447632, "pid": 269, "hostname": "Nicolass-Air.technicolor.net", "node_ip": "127.0.0.1", "config": {"exp_name": "QREPS", "seed": 1, "torch_deterministic": true, "cuda": true, "track": false, "wandb_project_name": "QREPS_CartPole-v1", "wandb_entity": "TFG", "capture_video": false, "env_id": "CartPole-v1", "total_timesteps": 200, "num_updates": 40, "buffer_size": 10000, "update_epochs": 450, "update_policy_epochs": 100, "num_rollouts": 1, "num_envs": 2, "gamma": 0.99, "policy_lr_start": 0.003250226877551645, "policy_lr_end": 1.093370662985288e-05, "q_lr_start": 0.007976025327952099, "q_lr_end": 1.2534303604942787e-05, "alpha": 2.5079101787892424, "eta": 0.2672078095784446, "autotune": false, "target_entropy_scale": 0.1, "linear_schedule": false, "__trial_index__": 1}, "time_since_restore": 93.68392324447632, "iterations_since_restore": 31}
{"reward": 61.0, "timestamp": 1711467360, "checkpoint_dir_name": null, "done": false, "training_iteration": 32, "trial_id": "97b5cc17", "date": "2024-03-26_16-36-00", "time_this_iter_s": 3.2619149684906006, "time_total_s": 96.94583821296692, "pid": 269, "hostname": "Nicolass-Air.technicolor.net", "node_ip": "127.0.0.1", "config": {"exp_name": "QREPS", "seed": 1, "torch_deterministic": true, "cuda": true, "track": false, "wandb_project_name": "QREPS_CartPole-v1", "wandb_entity": "TFG", "capture_video": false, "env_id": "CartPole-v1", "total_timesteps": 200, "num_updates": 40, "buffer_size": 10000, "update_epochs": 450, "update_policy_epochs": 100, "num_rollouts": 1, "num_envs": 2, "gamma": 0.99, "policy_lr_start": 0.003250226877551645, "policy_lr_end": 1.093370662985288e-05, "q_lr_start": 0.007976025327952099, "q_lr_end": 1.2534303604942787e-05, "alpha": 2.5079101787892424, "eta": 0.2672078095784446, "autotune": false, "target_entropy_scale": 0.1, "linear_schedule": false, "__trial_index__": 1}, "time_since_restore": 96.94583821296692, "iterations_since_restore": 32}
{"reward": 61.0, "timestamp": 1711467363, "checkpoint_dir_name": null, "done": false, "training_iteration": 33, "trial_id": "97b5cc17", "date": "2024-03-26_16-36-03", "time_this_iter_s": 3.1288130283355713, "time_total_s": 100.07465124130249, "pid": 269, "hostname": "Nicolass-Air.technicolor.net", "node_ip": "127.0.0.1", "config": {"exp_name": "QREPS", "seed": 1, "torch_deterministic": true, "cuda": true, "track": false, "wandb_project_name": "QREPS_CartPole-v1", "wandb_entity": "TFG", "capture_video": false, "env_id": "CartPole-v1", "total_timesteps": 200, "num_updates": 40, "buffer_size": 10000, "update_epochs": 450, "update_policy_epochs": 100, "num_rollouts": 1, "num_envs": 2, "gamma": 0.99, "policy_lr_start": 0.003250226877551645, "policy_lr_end": 1.093370662985288e-05, "q_lr_start": 0.007976025327952099, "q_lr_end": 1.2534303604942787e-05, "alpha": 2.5079101787892424, "eta": 0.2672078095784446, "autotune": false, "target_entropy_scale": 0.1, "linear_schedule": false, "__trial_index__": 1}, "time_since_restore": 100.07465124130249, "iterations_since_restore": 33}
{"reward": 61.0, "timestamp": 1711467366, "checkpoint_dir_name": null, "done": false, "training_iteration": 34, "trial_id": "97b5cc17", "date": "2024-03-26_16-36-06", "time_this_iter_s": 3.2660560607910156, "time_total_s": 103.3407073020935, "pid": 269, "hostname": "Nicolass-Air.technicolor.net", "node_ip": "127.0.0.1", "config": {"exp_name": "QREPS", "seed": 1, "torch_deterministic": true, "cuda": true, "track": false, "wandb_project_name": "QREPS_CartPole-v1", "wandb_entity": "TFG", "capture_video": false, "env_id": "CartPole-v1", "total_timesteps": 200, "num_updates": 40, "buffer_size": 10000, "update_epochs": 450, "update_policy_epochs": 100, "num_rollouts": 1, "num_envs": 2, "gamma": 0.99, "policy_lr_start": 0.003250226877551645, "policy_lr_end": 1.093370662985288e-05, "q_lr_start": 0.007976025327952099, "q_lr_end": 1.2534303604942787e-05, "alpha": 2.5079101787892424, "eta": 0.2672078095784446, "autotune": false, "target_entropy_scale": 0.1, "linear_schedule": false, "__trial_index__": 1}, "time_since_restore": 103.3407073020935, "iterations_since_restore": 34}
{"reward": 61.0, "timestamp": 1711467369, "checkpoint_dir_name": null, "done": false, "training_iteration": 35, "trial_id": "97b5cc17", "date": "2024-03-26_16-36-09", "time_this_iter_s": 3.1738710403442383, "time_total_s": 106.51457834243774, "pid": 269, "hostname": "Nicolass-Air.technicolor.net", "node_ip": "127.0.0.1", "config": {"exp_name": "QREPS", "seed": 1, "torch_deterministic": true, "cuda": true, "track": false, "wandb_project_name": "QREPS_CartPole-v1", "wandb_entity": "TFG", "capture_video": false, "env_id": "CartPole-v1", "total_timesteps": 200, "num_updates": 40, "buffer_size": 10000, "update_epochs": 450, "update_policy_epochs": 100, "num_rollouts": 1, "num_envs": 2, "gamma": 0.99, "policy_lr_start": 0.003250226877551645, "policy_lr_end": 1.093370662985288e-05, "q_lr_start": 0.007976025327952099, "q_lr_end": 1.2534303604942787e-05, "alpha": 2.5079101787892424, "eta": 0.2672078095784446, "autotune": false, "target_entropy_scale": 0.1, "linear_schedule": false, "__trial_index__": 1}, "time_since_restore": 106.51457834243774, "iterations_since_restore": 35}
{"reward": 61.0, "timestamp": 1711467372, "checkpoint_dir_name": null, "done": false, "training_iteration": 36, "trial_id": "97b5cc17", "date": "2024-03-26_16-36-12", "time_this_iter_s": 3.095329999923706, "time_total_s": 109.60990834236145, "pid": 269, "hostname": "Nicolass-Air.technicolor.net", "node_ip": "127.0.0.1", "config": {"exp_name": "QREPS", "seed": 1, "torch_deterministic": true, "cuda": true, "track": false, "wandb_project_name": "QREPS_CartPole-v1", "wandb_entity": "TFG", "capture_video": false, "env_id": "CartPole-v1", "total_timesteps": 200, "num_updates": 40, "buffer_size": 10000, "update_epochs": 450, "update_policy_epochs": 100, "num_rollouts": 1, "num_envs": 2, "gamma": 0.99, "policy_lr_start": 0.003250226877551645, "policy_lr_end": 1.093370662985288e-05, "q_lr_start": 0.007976025327952099, "q_lr_end": 1.2534303604942787e-05, "alpha": 2.5079101787892424, "eta": 0.2672078095784446, "autotune": false, "target_entropy_scale": 0.1, "linear_schedule": false, "__trial_index__": 1}, "time_since_restore": 109.60990834236145, "iterations_since_restore": 36}
{"reward": 61.0, "timestamp": 1711467376, "checkpoint_dir_name": null, "done": false, "training_iteration": 37, "trial_id": "97b5cc17", "date": "2024-03-26_16-36-16", "time_this_iter_s": 3.606821060180664, "time_total_s": 113.21672940254211, "pid": 269, "hostname": "Nicolass-Air.technicolor.net", "node_ip": "127.0.0.1", "config": {"exp_name": "QREPS", "seed": 1, "torch_deterministic": true, "cuda": true, "track": false, "wandb_project_name": "QREPS_CartPole-v1", "wandb_entity": "TFG", "capture_video": false, "env_id": "CartPole-v1", "total_timesteps": 200, "num_updates": 40, "buffer_size": 10000, "update_epochs": 450, "update_policy_epochs": 100, "num_rollouts": 1, "num_envs": 2, "gamma": 0.99, "policy_lr_start": 0.003250226877551645, "policy_lr_end": 1.093370662985288e-05, "q_lr_start": 0.007976025327952099, "q_lr_end": 1.2534303604942787e-05, "alpha": 2.5079101787892424, "eta": 0.2672078095784446, "autotune": false, "target_entropy_scale": 0.1, "linear_schedule": false, "__trial_index__": 1}, "time_since_restore": 113.21672940254211, "iterations_since_restore": 37}
{"reward": 61.0, "timestamp": 1711467379, "checkpoint_dir_name": null, "done": false, "training_iteration": 38, "trial_id": "97b5cc17", "date": "2024-03-26_16-36-19", "time_this_iter_s": 3.279116153717041, "time_total_s": 116.49584555625916, "pid": 269, "hostname": "Nicolass-Air.technicolor.net", "node_ip": "127.0.0.1", "config": {"exp_name": "QREPS", "seed": 1, "torch_deterministic": true, "cuda": true, "track": false, "wandb_project_name": "QREPS_CartPole-v1", "wandb_entity": "TFG", "capture_video": false, "env_id": "CartPole-v1", "total_timesteps": 200, "num_updates": 40, "buffer_size": 10000, "update_epochs": 450, "update_policy_epochs": 100, "num_rollouts": 1, "num_envs": 2, "gamma": 0.99, "policy_lr_start": 0.003250226877551645, "policy_lr_end": 1.093370662985288e-05, "q_lr_start": 0.007976025327952099, "q_lr_end": 1.2534303604942787e-05, "alpha": 2.5079101787892424, "eta": 0.2672078095784446, "autotune": false, "target_entropy_scale": 0.1, "linear_schedule": false, "__trial_index__": 1}, "time_since_restore": 116.49584555625916, "iterations_since_restore": 38}
{"reward": 61.0, "timestamp": 1711467383, "checkpoint_dir_name": null, "done": false, "training_iteration": 39, "trial_id": "97b5cc17", "date": "2024-03-26_16-36-23", "time_this_iter_s": 3.3823060989379883, "time_total_s": 119.87815165519714, "pid": 269, "hostname": "Nicolass-Air.technicolor.net", "node_ip": "127.0.0.1", "config": {"exp_name": "QREPS", "seed": 1, "torch_deterministic": true, "cuda": true, "track": false, "wandb_project_name": "QREPS_CartPole-v1", "wandb_entity": "TFG", "capture_video": false, "env_id": "CartPole-v1", "total_timesteps": 200, "num_updates": 40, "buffer_size": 10000, "update_epochs": 450, "update_policy_epochs": 100, "num_rollouts": 1, "num_envs": 2, "gamma": 0.99, "policy_lr_start": 0.003250226877551645, "policy_lr_end": 1.093370662985288e-05, "q_lr_start": 0.007976025327952099, "q_lr_end": 1.2534303604942787e-05, "alpha": 2.5079101787892424, "eta": 0.2672078095784446, "autotune": false, "target_entropy_scale": 0.1, "linear_schedule": false, "__trial_index__": 1}, "time_since_restore": 119.87815165519714, "iterations_since_restore": 39}
{"reward": 61.0, "timestamp": 1711467386, "checkpoint_dir_name": null, "done": false, "training_iteration": 40, "trial_id": "97b5cc17", "date": "2024-03-26_16-36-26", "time_this_iter_s": 3.391201972961426, "time_total_s": 123.26935362815857, "pid": 269, "hostname": "Nicolass-Air.technicolor.net", "node_ip": "127.0.0.1", "config": {"exp_name": "QREPS", "seed": 1, "torch_deterministic": true, "cuda": true, "track": false, "wandb_project_name": "QREPS_CartPole-v1", "wandb_entity": "TFG", "capture_video": false, "env_id": "CartPole-v1", "total_timesteps": 200, "num_updates": 40, "buffer_size": 10000, "update_epochs": 450, "update_policy_epochs": 100, "num_rollouts": 1, "num_envs": 2, "gamma": 0.99, "policy_lr_start": 0.003250226877551645, "policy_lr_end": 1.093370662985288e-05, "q_lr_start": 0.007976025327952099, "q_lr_end": 1.2534303604942787e-05, "alpha": 2.5079101787892424, "eta": 0.2672078095784446, "autotune": false, "target_entropy_scale": 0.1, "linear_schedule": false, "__trial_index__": 1}, "time_since_restore": 123.26935362815857, "iterations_since_restore": 40}
